codigos/TP_Labs_Agustin/GP02/ej1/rtl/fpmul.v
//! @title Floating point multiplier
//! @author Agustin Matias Ortiz (aortiz@frba.utn.edu.ar)
//! @version 1.0
//! @date 24/09/2022
//!
//! @brief Unsigned accumulator with adder input selection
//! @details Multiplier of values whose format is: 
//!      
//! |bits    |  12  |  [11:8]  |   [7:0]  |
//! |---     |---   |---       |---       |
//! |function| Sign | Exponent | Mantissa |
//!      

`define COCOTB_SIM 1
`define bias 7

module fpmul 
(
    input  [12:0] i_data1, //! Data input
    input  [12:0] i_data2, //! Data input

    output reg [12:0] o_mul    //! Result
);
//-----------arch-----------

    // Localparam
    localparam  [12:0] nan         = {{6{1'b1}},{7{1'b0}}};     //! Nan representation
    localparam  [11:0] inf         = {{4{1'b1}},{8{1'b0}}};     //! Inf representation
    localparam  [11:0] zero        = {1'b0,{3{1'b1}},{8{1'b0}}};//! Zero representation

    /*vars*/
    wire Sign;                    //! Calculation of sign of result
    reg         [7:0]  Mantissa ; //! Truncation of multiplication
    wire        [15:0] Mult_res ; //! Res of multiplication only
    wire        [5:0]  Sum_exp  ; //! Sum of exponent - bias
    wire               Nan_check; //! Check if result must be NaN
    wire              Zero_check; //! Check if result must be zero

    //! Sign 
    assign Sign = i_data1[12] ^ i_data2[12];

    //! Mantissa
    assign Mult_res = i_data1[7:0] * i_data2[7:0]; // U(16.14)
    
    //! Truncation, U(8.7) with rounding
    always @(*) begin : trunc                      
        if (Mult_res[7]) Mantissa <= Mult_res[15:8]+1;
        else             Mantissa <= Mult_res[15:8];
    end

    //! Exponent
    assign Sum_exp   = i_data1[11:8] + i_data2[11:8] - `bias; 


    //! Nan check
    assign Nan_check = (i_data1==nan || i_data2==nan)              ? 1'b1 :
                       (i_data1[11:0]==inf && i_data2[11:0]==zero) ? 1'b1 :
                       (i_data2[11:0]==inf && i_data1[11:0]==zero) ? 1'b1 : 1'b0 ;
    //! Zero check
    assign Zero_check= (i_data1[11:0]==zero || i_data2[11:0]==zero) ? 1'b1 :
                       (i_data1[11:8] + i_data2[11:8] < `bias)      ? 1'b1 : 1'b0 ;



    //! General operation
    always @(*) begin : exp_calc   
        // not a number 
        if (Nan_check)              o_mul <= nan;
        // case zero
        else if (Zero_check)        o_mul <= {Sign,zero};         
        // normal operation
        else if (~Sum_exp[4])       o_mul <= {Sign,Sum_exp[3:0],Mantissa};
        // +- inf

        else if (Sum_exp[4])        o_mul <= {Sign,inf};

        else                        o_mul <= nan;

    end

    /*===============*/
    /* for cocotb sim*/
    /*===============*/
    `ifdef COCOTB_SIM
    initial begin
    $dumpfile ("fpmul.vcd");
    $dumpvars (0, fpmul);
    #1;
    end
    `endif

endmodule

codigos/TP_Labs_Agustin/GP02/ej1/sim/fpmul.vcd
$date
	Wed Nov  2 19:03:44 2022
$end
$version
	Icarus Verilog
$end
$timescale
	1ps
$end
$scope module fpmul $end
$var wire 1 ! Sign $end
$var wire 13 " i_data1 [12:0] $end
$var wire 13 # i_data2 [12:0] $end
$var wire 1 $ Zero_check $end
$var wire 6 % Sum_exp [5:0] $end
$var wire 1 & Nan_check $end
$var wire 16 ' Mult_res [15:0] $end
$var reg 8 ( Mantissa [7:0] $end
$var reg 13 ) o_mul [12:0] $end
$scope begin exp_calc $end
$upscope $end
$scope begin trunc $end
$upscope $end
$upscope $end
$enddefinitions $end
#0
$dumpvars
b11100000000 )
b0 (
b0 '
0&
b111001 %
1$
b0 #
b0 "
0!
$end
#200000
b1000000 (
b1111110000000 )
0$
1&
b100000000000000 '
b10111 %
b1111110000000 "
b1111110000000 #
#210000
b0 (
1!
b0 '
b111100000000 #
#220000
0!
b1111100000000 #
#230000
1$
1!
b1111 %
b11100000000 #
#240000
0!
b1011100000000 #
#250000
0$
1!
b0 '
b10111 %
b111100000000 "
b1111110000000 #
#260000
b111100000000 )
0!
0&
b111100000000 #
#270000
b1111100000000 )
1!
b1111100000000 #
#280000
b1111110000000 )
1&
1$
0!
b1111 %
b11100000000 #
#290000
1!
b1011100000000 #
#300000
0$
0!
b10111 %
b1111100000000 "
b1111110000000 #
#310000
b1111100000000 )
1!
0&
b111100000000 #
#320000
b111100000000 )
0!
b1111100000000 #
#330000
b1111110000000 )
1&
1$
1!
b1111 %
b11100000000 #
#340000
0!
b1011100000000 #
#350000
1!
b1111 %
b11100000000 "
b1111110000000 #
#360000
b1111110000000 )
0!
1&
b111100000000 #
#370000
1!
b1111100000000 #
#380000
b11100000000 )
0&
0!
b111 %
b11100000000 #
#390000
b1011100000000 )
1!
b1011100000000 #
#400000
b1111110000000 )
0!
1&
b1111 %
b1011100000000 "
b1111110000000 #
#410000
b1111110000000 )
1!
1&
b111100000000 #
#420000
0!
b1111100000000 #
#430000
b1011100000000 )
0&
1!
b111 %
b11100000000 #
#440000
b11100000000 )
0!
b1011100000000 #
#450001
b111001 %
b0 "
b0 #
b11100000000 )
#650001
b1000000 (
b100000000000000 '
b111011 %
b110000000 "
b110000000 #
#660001
b111111 %
b1110000000 "
b1110000000 #
#670001
b111100000000 )
b1000010 (
0$
b100001000000100 '
b10111 %
b1111110000010 "
b1111110000010 #
#680002
b0 (
1$
b0 '
b111001 %
b0 "
b0 #
b11100000000 )
#880002
b111011 (
b11101100011001 '
b111011 %
b1000101111011 "
b1000101111011 #
#890002
b1000101010011 )
b1010011 (
0$
1!
b101001010100100 '
b1 %
b11110101100 #
#900002
b111100 (
b1010000111100 )
b11101110010100 '
b100 %
b101001111100 #
#910002
b10110 (
b1011000010110 )
b1011000011010 '
b110 %
b110000101110 #
#920002
b1100111 (
b100001100111 )
0!
b110011011010010 '
b1000 %
b1111011010110 #
#930002
b1001101100111 )
1!
b110011101001101 '
b11 %
b100111010111 #
#940002
b100101 (
b1000100100101 )
b10010101111010 '
b1 %
b11101001110 #
#950002
b11101 (
b10000011101 )
0!
b1110101001111 '
b100 %
b1101000111101 #
#960002
b1100100 (
b100001100100 )
b110010001101011 '
b1000 %
b1111011010001 #
#970002
b1000100 (
b11100000000 )
1$
b100001110111111 '
b111100 %
b1001010001101 #
#980002
b1000000001001 )
b1001 (
0$
1!
b100100100001 '
b0 %
b11000010011 #
#990002
b100101 (
b1011100000000 )
1$
b10010010000100 '
b111101 %
b1101001100 #
#1000002
b1001101010000 )
b1010000 (
0$
b100111111000010 '
b11 %
b100110100110 #
#1010002
b1010100 (
b1011100000000 )
1$
b101001110011010 '
b111110 %
b10010101110 #
#1020002
b1000101000000 )
b1000000 (
0$
b100000001100010 '
b1 %
b11110000110 #
#1030002
b1000101010011 )
b1010011 (
b101001010100100 '
b1 %
b11110101100 "
b1000101111011 #
#1040002
b1110100 (
b11101110100 )
0!
b111001110010000 '
b111 %
b11110101100 #
#1050002
b1010011 (
b101001010011 )
b101001101010000 '
b1010 %
b101001111100 #
#1060002
b11111 (
b110000011111 )
b1111011101000 '
b1100 %
b110000101110 #
#1070002
b10010000 (
b1111010010000 )
1!
b1000111111001000 '
b1110 %
b1111011010110 #
#1080002
b100110010000 )
0!
b1001000001110100 '
b1001 %
b100111010111 #
#1090002
b110100 (
b11100110100 )
b11010001101000 '
b111 %
b11101001110 #
#1100002
b101001 (
b1101000101001 )
1!
b10100011111100 '
b1010 %
b1101000111101 #
#1110002
b10001100 (
b1111010001100 )
b1000110001101100 '
b1110 %
b1111011010001 #
#1120002
b1011111 (
b1001001011111 )
b101111010111100 '
b10 %
b1001010001101 #
#1130002
b1101 (
b11000001101 )
0!
b110011000100 '
b110 %
b11000010011 #
#1140002
b110011 (
b1100110011 )
b11001100010000 '
b11 %
b1101001100 #
#1150002
b1110000 (
b100101110000 )
b110111110001000 '
b1001 %
b100110100110 #
#1160002
b1110101 (
b10001110101 )
b111010011101000 '
b100 %
b10010101110 #
#1170002
b1011010 (
b11101011010 )
b101101000001000 '
b111 %
b11110000110 #
#1180002
b111100 (
b1010000111100 )
1!
b11101110010100 '
b100 %
b101001111100 "
b1000101111011 #
#1190002
b1010011 (
b101001010011 )
0!
b101001101010000 '
b1010 %
b11110101100 #
#1200002
b111100 (
b110100111100 )
b11110000010000 '
b1101 %
b101001111100 #
#1210002
b10110 (
b111100010110 )
b1011001001000 '
b1111 %
b110000101110 #
#1220002
b1101000 (
b1111100000000 )
1!
b110011110101000 '
b10001 %
b1111011010110 #
#1230002
b110001101000 )
0!
b110100000100100 '
b1100 %
b100111010111 #
#1240002
b100110 (
b101000100110 )
b10010111001000 '
b1010 %
b11101001110 #
#1250002
b11110 (
b1110100011110 )
1!
b1110110001100 '
b1101 %
b1101000111101 #
#1260002
b1100101 (
b1111100000000 )
b110010100111100 '
b10001 %
b1111011010001 #
#1270002
b1000100 (
b1010101000100 )
b100010001001100 '
b101 %
b1001010001101 #
#1280002
b1001 (
b100100001001 )
0!
b100100110100 '
b1001 %
b11000010011 #
#1290002
b100101 (
b11000100101 )
b10010011010000 '
b110 %
b1101001100 #
#1300002
b1010000 (
b110001010000 )
b101000001101000 '
b1100 %
b100110100110 #
#1310002
b1010100 (
b11101010100 )
b101010001001000 '
b111 %
b10010101110 #
#1320002
b1000001 (
b101001000001 )
b100000011101000 '
b1010 %
b11110000110 #
#1330002
b10110 (
b1011000010110 )
1!
b1011000011010 '
b110 %
b110000101110 "
b1000101111011 #
#1340002
b11111 (
b110000011111 )
0!
b1111011101000 '
b1100 %
b11110101100 #
#1350002
b10110 (
b111100010110 )
b1011001001000 '
b1111 %
b101001111100 #
#1360002
b1000 (
b111100000000 )
b100001000100 '
b10001 %
b110000101110 #
#1370002
b1111100000000 )
b100110 (
1!
b10011001110100 '
b10011 %
b1111011010110 #
#1380002
b100111 (
b111000100111 )
0!
b10011010100010 '
b1110 %
b100111010111 #
#1390002
b1110 (
b110000001110 )
b111000000100 '
b1100 %
b11101001110 #
#1400002
b1011 (
b1111100001011 )
1!
b101011110110 '
b1111 %
b1101000111101 #
#1410002
b100110 (
b1111100000000 )
b10010110001110 '
b10011 %
b1111011010001 #
#1420002
b11001 (
b1011100011001 )
b1100101010110 '
b111 %
b1001010001101 #
#1430002
b11 (
b101100000011 )
0!
b1101101010 '
b1011 %
b11000010011 #
