codigos/TP_Labs_Agustin/GP01/ej4/rtl/diffeq.v
//! @title  Differential equation
//! @author Agustin Matias Ortiz (aortiz@frba.utn.edu.ar)
//! @version 1.0
//! @date 02/09/2022
//!
//! @brief Ordinary differential equation
//! @details A circuit is implemented that performs the following 
//! differential equation:
//! y[n] = x[n] −x[n −1] + x[n −2] + x[n −3] + 0,5y[n −1] + 0,25y[n −2]
//! Rewriting to pool registers as delays (Y = Y(Z)):
//! -
//! ![eq](https://latex.codecogs.com/gif.latex?Y=X+Z^{-3}X+Z^{-2}(0.25Y+X)+.Z^{-1}(0.5Y-X\))


`define COCOTB_SIM 1
// Definitions
//`define N 16

module diffeq 
#(  // Parameters
    parameter N    = 16   //! Word lenght
)
(
    output reg signed [N-1:0] o_y   , //! output register

    input      signed [N-1:0] i_x   , //! Input signal

    input            clk    , //! Clock
    input            i_rst    //! Asynchronous reset active low
);

//-----------arch-----------

    /*vars*/
    reg signed [N:0] reg1,reg2,reg3;     //!unit delays

    //! Delays register with asynchronous reset
    always @(posedge clk or posedge i_rst) begin: Delays
        if(i_rst) begin
            reg1 <= {N{1'b0}};
            reg2 <= {N{1'b0}};
            reg3 <= {N{1'b0}};
            o_y  <= {N{1'b0}};
        end
        else begin 
            reg1 <= {1'b0,i_x};
            reg2 <= i_x + reg1 + (o_y >>> 2); //0.25 Y
            reg3 <= reg2 - i_x + (o_y >>> 2); //0.5
            o_y  <= i_x + reg3;
        end
    end

    /*===============*/
    /* for cocotb sim*/
    /*===============*/
    `ifdef COCOTB_SIM
    initial begin
    $dumpfile ("diffeq.vcd");
    $dumpvars (0, diffeq);
    #1;
    end
    `endif
endmodule

codigos/TP_Labs_Agustin/GP01/ej4/sim/diffeq.vcd
$date
	Sat Sep 24 19:56:19 2022
$end
$version
	Icarus Verilog
$end
$timescale
	1ps
$end
$scope module diffeq $end
$var wire 1 ! clk $end
$var wire 1 " i_rst $end
$var wire 16 # i_x [15:0] $end
$var reg 16 $ o_y [15:0] $end
$var reg 17 % reg1 [16:0] $end
$var reg 17 & reg2 [16:0] $end
$var reg 17 ' reg3 [16:0] $end
$upscope $end
$enddefinitions $end
#0
$dumpvars
b0 '
b0 &
b0 %
b0 $
b0 #
1"
0!
$end
#5000
1!
#10000
0!
#15000
1!
#20000
0!
#25000
1!
#30000
0!
#35000
1!
#40000
0!
#45000
1!
#50000
0!
#55000
1!
#60000
0!
#65000
1!
#70000
0!
#75000
1!
#80000
0!
#85000
1!
#90000
0!
#95000
1!
#100000
0!
#105000
1!
#110000
0!
#115000
1!
#120000
0!
#125000
1!
#130000
0!
#135000
1!
#140000
0!
#145000
1!
#150000
0!
#155000
1!
#160000
0!
#165000
1!
#170000
0!
#175000
1!
#180000
0!
#185000
1!
#190000
0!
#195000
1!
#200000
0"
b1100000101000000 #
0!
#205000
b1100000101000000 $
b11111011000000 '
b11100000101000000 &
b1100000101000000 %
1!
#210000
b1100010000001001 #
0!
#215000
b1011001001 $
b11110110110000111 '
b111010110011001 &
b1100010000001001 %
1!
#220000
b11011010110000 #
0!
#225000
b10010000110111 $
b11111110011011 '
b1111101101101011 &
b11011010110000 %
1!
#230000
b10001011011111 #
0!
#235000
b110001001111010 $
b1110000110011001 '
b110001010011100 &
b10001011011111 %
1!
#240000
b1101101001101111 #
0!
#245000
b1011110000001000 $
b1010000011001011 '
b1010111101100 &
b1101101001101111 %
1!
#250000
b1110010110101111 #
0!
#255000
b1000011001111010 $
b1111100111111 '
b1010111100100000 &
b1110010110101111 %
1!
#260000
b1100010100100011 #
0!
#265000
b1110010001100010 $
b1100101110011011 '
b1000110001110000 &
b1100010100100011 %
1!
#270000
b1100001011101010 #
0!
#275000
b1000111010000101 $
b1100001010011110 '
b1000000100100101 &
b1100001011101010 %
1!
#280000
b1110010100110011 #
0!
#285000
b1010011111010001 $
b111111110010011 '
b1000101110111110 &
b1110010100110011 %
1!
#290000
b1100100010001101 #
0!
#295000
b100100000100000 $
b1010110100100101 '
b1001011110110100 &
b1100100010001101 %
1!
#300000
b1110011011100001 #
0!
#305000
b1001010000000110 $
b1100001011011011 '
b1100000101110110 &
b1110011011100001 %
1!
#310000
b1101100101101001 #
0!
#315000
b1001110001000100 $
b1100110100001110 '
b1010010101001011 &
b1101100101101001 %
1!
#320000
b1100111011001101 #
0!
#325000
b1001101111011011 $
b1011110110001111 '
b1000111101000111 &
b1100111011001101 %
1!
#330000
b11101001101000 #
0!
#335000
b1111011111110111 $
b11101111010101 '
b1111000000101011 &
b11101001101000 %
1!
#340000
b1111111111010 #
0!
#345000
b101101111001111 $
b1100111000101110 '
b101100001011111 &
b1111111111010 %
1!
#350000
b1100001111100100 #
0!
#355000
b1001001000010010 $
b1010101101101110 '
b11111101011010001 &
b1100001111100100 %
1!
#360000
b110101011 #
0!
#365000
b1010110100011001 $
b11101110110101010 '
b1010101000010011 &
b110101011 %
1!
#370000
b1100110101001100 #
0!
#375000
b1010101011110110 $
b1100100000001101 '
b11011101000111101 &
b1100110101001100 %
1!
#380000
b11110111000100 #
0!
#385000
b10111010001 $
b10110011100110110 '
b1111010111001101 &
b11110111000100 %
1!
#390000
b1110100101100000 #
0!
#395000
b101000010010110 $
b10000110111100001 '
b10100010011000 &
b1110100101100000 %
1!
#400000
b110000 #
0!
#405000
b111000010001 $
b11110010001101 '
b1111110110110101 &
b110000 %
1!
#410000
b10111001000000 #
0!
#415000
b110101011001101 $
b1101001011111001 '
b11000111110100 &
b10111001000000 %
1!
#420000
b1111110011100111 #
0!
#425000
b1100111111100000 $
b100111111000000 '
b100010111011010 &
b1111110011100111 %
1!
#430000
b1001000101000 #
0!
#435000
b110000111101000 $
b10011110101010 '
b10000001100000111 &
b1001000101000 %
1!
#440000
b10100110100 #
0!
#445000
b10110011011110 $
b10001011001001101 '
b10111111010110 &
b10100110100 %
1!
#450000
b1111011100000011 #
0!
#455000
b110101010000 $
b100010000001010 '
b11101101110 &
b1111011100000011 %
1!
#460000
b101110000010 #
0!
#465000
b100111110001100 $
b11111111101000000 '
b10000010111011001 &
b101110000010 %
1!
#470000
b1101011001101010 #
0!
#475000
b1101010110101010 $
b10100001101010010 '
b11111010111001111 &
b1101011001101010 %
1!
#480000
b1101100100111010 #
0!
#485000
b1110010001100 $
b1000111111111 '
b1010010100001110 &
b1101100100111010 %
1!
#490000
b1001101000001 #
0!
#495000
b10010101000000 $
b1001100011110000 '
b1111001110011110 &
b1001101000001 %
1!
#500000
b1010000000000 #
0!
#505000
b1010110011110000 $
b1110100011101110 '
b11000010010001 &
b1010000000000 %
1!
#510000
b1111001000001010 #
0!
#515000
b1101101011111000 $
b10100111000011 '
b11111000101000110 &
b1111001000001010 %
1!
#520000
b111011011100 #
0!
#525000
b11100010011111 $
b11101100100101000 '
b1111011110100100 &
b111011011100 %
1!
#530000
b1100010001100001 #
0!
#535000
b1001110110001001 $
b10100000101101010 '
b11110000101100100 &
b1100010001100001 %
1!
#540000
b1100000001000111 #
0!
#545000
b110110001 $
b100001111111 '
b110110000001010 &
b1100000001000111 %
1!
#550000
b1100100001110001 #
0!
#555000
b1101000011110000 $
b1010010000000101 '
b1000100100100100 &
b1100100001110001 %
1!
#560000
b1111101101000010 #
0!
#565000
b1001111101000111 $
b1000001000011110 '
b1011011111101111 &
b1111101101000010 %
1!
#570000
b10111111001001 #
0!
#575000
b1011000111100111 $
b110111111110111 '
b10001001011011100 &
b10111111001001 %
1!
#580000
b1100101110000 #
0!
#585000
b1000100101100111 $
b1110010111100101 '
b11010110110010 &
b1100101110000 %
1!
#590000
b100000001001 #
0!
#595000
b1110110111101110 $
b1000000000010 '
b1111010010 &
b100000001001 %
1!
#600000
b111111011100 #
0!
#605000
b1111111011110 $
b11110111101110001 '
b1001101100000 &
b111111011100 %
1!
#610000
b1101110011100 #
0!
#615000
b101100001101 $
b11111111110111011 '
b11001101101111 &
b1101110011100 %
1!
#620000
b1111110100111111 #
0!
#625000
b1111110011111010 $
b11100011110011 '
b1101110011110 &
b1111110100111111 %
1!
#630000
b1100100 #
0!
#635000
b11100101010111 $
b1101001111000 '
b1111110011100001 &
b1100100 %
1!
#640000
b111100010100 #
0!
#645000
b10100110001100 $
b1111110000100010 '
b1110111001101 &
b111100010100 %
1!
#650000
b1111110011001000 #
0!
#655000
b1111100011101010 $
b10101101101000 '
b1011000111111 &
b1111110011001000 %
1!
#660000
b1110101000011011 #
0!
#665000
b1010110000011 $
b10101001011110 '
b1110010100011101 &
b1110101000011011 %
1!
#670000
b1110011001110000 #
0!
#675000
b1000011001110 $
b10000010000001101 '
b1101010111101011 &
b1110011001110000 %
1!
#680000
b11100011001100 #
0!
#685000
b11110011011001 $
b1010000101010010 '
b10010001101101111 &
b11100011001100 %
1!
#690000
b10000011010000 #
0!
#695000
b1100001000100010 $
b10001000111010101 '
b110100011010010 &
b10000011010000 %
1!
#700000
b1101110001000111 #
0!
#705000
b1110111000011100 $
b111110100010011 '
b11110110110011111 &
b1101110001000111 %
1!
#710000
b10111100010010 #
0!
#715000
b1010110000100101 $
b11011101000010100 '
b10000011011100000 &
b10111100010010 %
1!
#720000
b1101011000100110 #
0!
#725000
b1001000000111010 $
b10001101111000011 '
b11111000001000001 &
b1101011000100110 %
1!
#730000
b1110101010111111 #
0!
#735000
b11010000010 $
b11110100110010000 '
b1010010011110011 &
b1110101010111111 %
1!
#740000
b101000011000 #
0!
#745000
b1111001110101000 $
b1001110001111011 '
b1111011001110111 &
b101000011000 %
1!
#750000
b1010011110101 #
0!
#755000
b1011000101110000 $
b1101111001101100 '
b1101111110111 &
b1010011110101 %
1!
#760000
b11101100101110 #
0!
#765000
b1100110011010 $
b11100110100100101 '
b11110001111111 &
b11101100101110 %
1!
#770000
b10111011111110 #
0!
#775000
b1111110000100011 $
b1001111100111 '
b111000010010010 &
b10111011111110 %
1!
#780000
b1100000111111100 #
0!
#785000
b1101010111100011 $
b1010110110011110 '
b11111000000000010 &
b1100000111111100 %
1!
#790000
b11110101010101 #
0!
#795000
b1110101011110011 $
b11010100000100101 '
b1111010011001001 &
b11110101010101 %
1!
#800000
b101000101011 #
0!
#805000
b1011001001010000 $
b1110010101011010 '
b100001000111100 &
b101000101011 %
1!
#810000
b1110011001110010 #
0!
#815000
b1100101111001100 $
b100100001011110 '
b11101110100110001 &
b1110011001110010 %
1!
#820000
b1110101111110100 #
0!
#825000
b11010001010010 $
b11110010000110000 '
b1100010101011001 &
b1110101111110100 %
1!
#830000
b1111101110100001 #
0!
#835000
b1101111111010001 $
b1101011011001100 '
b1111010010101001 &
b1111101110100001 %
1!
