codigos/GP02/ej4/rtl/fir_direct.v
// utility site: https://chummersone.github.io/qformat.html
//               http://t-filter.engineerjs.com/
//               http://www.fdi.ucm.es/profesor/mendias/das/docs/DAStema6.pdf
//               https://www.airsupplylab.com/verilog-fpga/83-fpga-lesson-04-verilog-scalar,-vector,-and-array.html#arrays
`define COCOTB_SIM 1

module fir_direct 
#(
    parameter NTAPS = 4
) 
(
    output     signed [17:0] o_y            , //! output register

    input      signed [15:0] i_x            , //! Input signal 
    
    input            clk                    , //! Clock
    input            i_rst                    //! Asynchronous reset active low
    );
    //-----------arch-----------

    localparam  [15:0] zero        = {{16{1'b0}}};//! Zeros 
    localparam  [15:0] ones        = {{16{1'b1}}};//! Ones
    
    /*vars*/
    integer idx=0;
    reg signed [15:0] i_h        [NTAPS-1:0] ; 
    reg signed [15:0] FiltReg    [NTAPS-2:0] ;
    reg signed [31:0] Mult       [NTAPS-1:0] ;
    reg signed [17:0] Sum        [NTAPS-1:0] ;

    reg signed [31:0] Temp_mul_0      ;
    reg signed [31:0] Temp_mul_1      ;
    reg signed [31:0] Temp_mul_2      ;
    reg signed [31:0] Temp_mul_3      ;

    //! Hardcode coeff
    always @(negedge i_rst) begin: coefficient_load
        i_h[0]=16'h001e;
        i_h[1]=16'h46b6;
        i_h[2]=16'h46b6;
        i_h[3]=16'h001e;     
    end

    //! Performs a N taps filter
    always @(posedge clk ) begin: registers
        if(i_rst) begin
            for(idx=0; idx<NTAPS-1; idx=idx+1) begin
                FiltReg[idx] <= zero;
            end
        end 
        else begin
            FiltReg[0] <= i_x;
            for(idx=0; idx<NTAPS-2; idx=idx+1) begin
                FiltReg[idx+1] <= FiltReg[idx];
            end
        end
    end

    //! Multiplication
    always @(posedge clk ) begin:Multiplication
        if(i_rst) begin
            for(idx=0; idx<NTAPS-1; idx=idx+1) begin
                Mult[idx] <=0;
            end
        end 
        else begin
            Mult[0] <= i_h[0]*i_x;
            for(idx=1; idx<NTAPS; idx=idx+1) begin
                Mult[idx] <= i_h[idx]*FiltReg[idx-1];
            end
        end
    end

    //! Addition
    always @(posedge clk ) begin:Addition
        if(i_rst) begin
            for(idx=0; idx<NTAPS-1; idx=idx+1) begin
               Sum [idx] <={18'b0};
            end
            Temp_mul_0  <= 0;
            Temp_mul_1  <= 0;
            Temp_mul_2  <= 0;
            Temp_mul_3  <= 0;
        end 
        else begin
            Temp_mul_0  <= Mult[0];
            Temp_mul_1  <= Mult[1];
            Temp_mul_2  <= Mult[2];
            Temp_mul_3  <= Mult[3];
            Sum[0]      <= Temp_mul_0[30:15];
            Sum[1]      <= Temp_mul_1[30:15]+Temp_mul_0[30:15];
            Sum[2]      <= Temp_mul_2[30:15]+Temp_mul_1[30:15];
            Sum[3]      <= Temp_mul_3[30:15]+Temp_mul_2[30:15];
        end
    end
    assign o_y = Sum[3];

    /*===============*/
    /* for cocotb sim*/
    /*===============*/
    `ifdef COCOTB_SIM
    initial begin
    $dumpfile ("fir_direct.vcd");
    $dumpvars (0, fir_direct);
    #1;
    end
    `endif
endmodule

codigos/GP02/ej4/sim/fir_direct.vcd
$date
	Sun Oct 23 16:00:47 2022
$end
$version
	Icarus Verilog
$end
$timescale
	1ps
$end
$scope module fir_direct $end
$var wire 1 ! clk $end
$var wire 1 " i_rst $end
$var wire 16 # i_x [15:0] $end
$var wire 18 $ o_y [17:0] $end
$var reg 32 % Temp_mul_0 [31:0] $end
$var reg 32 & Temp_mul_1 [31:0] $end
$var reg 32 ' Temp_mul_2 [31:0] $end
$var reg 32 ( Temp_mul_3 [31:0] $end
$var integer 32 ) idx [31:0] $end
$scope begin Addition $end
$upscope $end
$scope begin Multiplication $end
$upscope $end
$scope begin coefficient_load $end
$upscope $end
$scope begin registers $end
$upscope $end
$upscope $end
$enddefinitions $end
#0
$dumpvars
b0 )
bx (
bx '
bx &
bx %
b0 $
b0 #
1"
0!
$end
#5000
b0 (
b0 '
b0 &
b0 %
b11 )
1!
#10000
0!
#15000
b11 )
1!
#20000
0!
#25000
b11 )
1!
#30000
0!
#35000
b11 )
1!
#40000
0!
#45000
b11 )
1!
#50000
0"
b1111111111111111 #
0!
#55000
bx (
b100 )
1!
#60000
0!
#65000
bx $
b0 (
b11111111111111111111111111100010 %
b100 )
1!
#70000
0!
#75000
b0 $
b11111111111111111011100101001010 &
b100 )
1!
#80000
0!
#85000
b11111111111111111011100101001010 '
b100 )
1!
#90000
0!
#95000
b1111111111111111 $
b11111111111111111111111111100010 (
b100 )
1!
#100000
0!
#105000
b11111111111111110 $
b100 )
1!
#110000
0!
#115000
b100 )
1!
#120000
0!
#125000
b100 )
1!
