codigos/TP_Labs_Agustin/GP02/ej4/rtl/fir_direct.v
//! @title Semi-generic FIR filter
//! @author Agustin Matias Ortiz (aortiz@frba.utn.edu.ar)
//! @version 1.0
//! @date 01/11/2022
//!
//! @brief 4 TAPS FIR filter
//! @details Although it is strictly a 4-stage transposed FIR, it is described in 
//! such a way that it is easily scalable to more stages, however, the coefficients are imposed in the design. 
//!
//! ### utility site: 
//!
//! - https://chummersone.github.io/qformat.html 
//!
//! - http://t-filter.engineerjs.com/
//!
//! - http://www.fdi.ucm.es/profesor/mendias/das/docs/DAStema6.pdf
//!
//! - https://www.airsupplylab.com/verilog-fpga/83-fpga-lesson-04-verilog-scalar,-vector,-and-array.html#arrays
`define COCOTB_SIM 1

module fir_direct 
#(
    parameter NTAPS = 4                       //! Filter stages
) 
(
    output     signed [17:0] o_y            , //! Output signal

    input      signed [15:0] i_x            , //! Input signal 
    
    input            clk                    , //! Clock
    input            i_rst                    //! Asynchronous reset active low
    );
    //-----------arch-----------

    localparam  [15:0] zero    = {{16{1'b0}}} ;   //! Zeros 
    
    //! generics vars
    integer     idx=0                         ;   //! Index for generic processes
    reg signed  [15:0] i_h        [NTAPS-1:0] ;   //! Coefficients array
    reg signed  [15:0] FiltReg    [NTAPS-2:0] ;   //! Filter registers array
    reg signed  [31:0] Mult       [NTAPS-1:0] ;   //! Multiplier registers array
    wire signed [17:0] Sum        [NTAPS-2:0] ;   //! Adder results array
    
    //! simples vars
    wire signed [31:0] Temp_mul_0             ;   //! Auxiliary vector for clipping truncation of the multiplier 
    wire signed [31:0] Temp_mul_1             ;   //! Auxiliary vector for clipping truncation of the multiplier
    wire signed [31:0] Temp_mul_2             ;   //! Auxiliary vector for clipping truncation of the multiplier
    wire signed [31:0] Temp_mul_3             ;   //! Auxiliary vector for clipping truncation of the multiplier

    //! Hardcode coeff load to register
    always @(posedge i_rst) begin: Coefficient_load
        i_h[0]=16'h8000;
        i_h[1]=16'h8000;
        i_h[2]=16'h8000;
        /* i_h[1]=16'h46b6;
        i_h[2]=16'h46b6; */
        i_h[3]=16'h8000;     
    end

    //! Generic load of registers
    always @(posedge clk ) begin: Registers
        if(i_rst) begin
            for(idx=0; idx<NTAPS-1; idx=idx+1) begin
                FiltReg[idx] <= zero;
            end
        end 
        else begin
            FiltReg[0] <= i_x;
            for(idx=0; idx<NTAPS-2; idx=idx+1) begin
                FiltReg[idx+1] <= FiltReg[idx];
            end
        end
    end

    //! Generic multiplication
    always @(posedge clk ) begin:Multiplication 
        if(i_rst) begin
            for(idx=0; idx<NTAPS-1; idx=idx+1) begin
                Mult[idx] <=0;
            end
        end 
        else begin
            Mult[0] <= i_h[0]*i_x;
            for(idx=1; idx<NTAPS; idx=idx+1) begin
                Mult[idx] <= i_h[idx]*FiltReg[idx-1];
            end
        end
    end

    //! Addition
    assign Temp_mul_0   = Mult[0];
    assign Temp_mul_1   = Mult[1];
    assign Temp_mul_2   = Mult[2];
    assign Temp_mul_3   = Mult[3];
    assign Sum[0]       = {Temp_mul_0[30],Temp_mul_0[30],Temp_mul_0[30:15]};
    assign Sum[1]       = {Temp_mul_1[30],Temp_mul_1[30],Temp_mul_1[30:15]}+Sum[0];
    assign Sum[2]       = {Temp_mul_2[30],Temp_mul_2[30],Temp_mul_2[30:15]}+Sum[1];
    assign o_y          = {Temp_mul_3[30],Temp_mul_3[30],Temp_mul_3[30:15]}+Sum[2];
 
    /*===============*/
    /* for cocotb sim*/
    /*===============*/
    `ifdef COCOTB_SIM
    initial begin
    $dumpfile ("fir_direct.vcd");
    $dumpvars (0, fir_direct);
    #1;
    end
    `endif
endmodule

codigos/TP_Labs_Agustin/GP02/ej4/sim/fir_direct.vcd
$date
	Sat Nov  5 17:41:05 2022
$end
$version
	Icarus Verilog
$end
$timescale
	1ps
$end
$scope module fir_direct $end
$var wire 32 ! Temp_mul_0 [31:0] $end
$var wire 32 " Temp_mul_1 [31:0] $end
$var wire 32 # Temp_mul_2 [31:0] $end
$var wire 32 $ Temp_mul_3 [31:0] $end
$var wire 1 % clk $end
$var wire 1 & i_rst $end
$var wire 16 ' i_x [15:0] $end
$var wire 18 ( o_y [17:0] $end
$var integer 32 ) idx [31:0] $end
$scope begin Coefficient_load $end
$upscope $end
$scope begin Multiplication $end
$upscope $end
$scope begin Registers $end
$upscope $end
$upscope $end
$enddefinitions $end
#0
$dumpvars
b11 )
bx (
b0 '
1&
1%
bx $
b0 #
b0 "
b0 !
$end
#5000
0%
#10000
b11 )
1%
#15000
0%
#20000
b11 )
1%
#25000
0%
#30000
b11 )
1%
#35000
0%
#40000
b11 )
1%
#45000
0%
#50000
b0 (
b0 $
b100 )
0&
1%
#55000
0%
#60000
b111000000000000000 (
b1000000000000000000000000000000 !
b100 )
b1000000000000000 '
1%
#65000
0%
#70000
b110000000000000000 (
b1000000000000000000000000000000 "
b100 )
1%
#75000
0%
#80000
b101000000000000000 (
b1000000000000000000000000000000 #
b100 )
1%
#85000
0%
#90000
b100000000000000000 (
b1000000000000000000000000000000 $
b100 )
1%
#95000
0%
#100000
b100 )
1%
#105000
0%
#110000
b100 )
1%
#115000
0%
#120000
b100 )
1%
#125000
0%
#130000
b100 )
1%
