codigos/GP01/ej1/uns_acc.v
//! @title  Unsigned accumulator
//! @author Agustin Matias Ortiz (aortiz@frba.utn.edu.ar)
//! @version 1.0
//! @date 02/09/2022
//!
//! @brief Unsigned accumulator with adder input selection
//! @details Given the extension of the input word that the 
//! statement shows, it is assumed that it is an unsigned 
//! circuit and therefore it is appropriate to speak of Carry and not Overflow.

module uns_acc
(
    output reg [5:0] o_data , //! Acc output
    output           o_carry, //! Carry output

    input      [2:0] i_data2, //! Data imput
    input      [2:0] i_data1, //! Data imput
    input      [1:0] i_sel  , //! Input selection signal

    input            clk    , //! Clock
    input            i_rst_n  //! Asynchronous reset active low
);
//-----------arch-----------

    /*vars*/
    wire [3:0] ext_data1,ext_data2; //!word extention
    reg  [3:0] sel_out;             //!input MUX
    wire [6:0] adder_out;           //!next state adder output

    //!Mux of selection of the input data to accumulate
    always @(*) begin :input_selector
        case (i_sel)
            2'b00: 
                    sel_out = {1'b0,i_data2};
            2'b01: 
                    sel_out = i_data2 + i_data1;
            2'b10: 
                    sel_out = {1'b0,i_data1};
            2'b11: 
                    sel_out = {3{1'b0}};
            default: 
                    sel_out = {3{1'b0}};
        endcase
    end

    //!next state adder
    assign adder_out = o_data + {2'b00,sel_out};

    //!accumulator register
    always @(posedge clk or negedge i_rst_n) begin:accumulator
        if(! i_rst_n) begin
            o_data <= {5{1'b0}};
        end
        else begin 
            o_data <= adder_out[5:0];
        end
    end

    assign o_carry = adder_out[6];

endmodule

codigos/GP01/ej1/uns_acc.vcd
$date
	Thu Sep 22 00:55:54 2022
$end
$version
	Icarus Verilog
$end
$timescale
	1ps
$end
$scope module uns_acc $end
$var wire 1 ! clk $end
$var wire 3 " i_data1 [2:0] $end
$var wire 3 # i_data2 [2:0] $end
$var wire 1 $ i_rst_n $end
$var wire 2 % i_sel [1:0] $end
$var wire 1 & o_carry $end
$var wire 7 ' adder_out [6:0] $end
$var reg 6 ( o_data [5:0] $end
$var reg 4 ) sel_out [3:0] $end
$scope begin accumulator $end
$upscope $end
$scope begin input_selector $end
$upscope $end
$upscope $end
$enddefinitions $end
#0
$dumpvars
b0 )
b0 (
b0 '
0&
b0 %
0$
b0 #
b0 "
1!
$end
#10000
0!
#20000
1!
#30000
0!
#40000
1!
#50000
0!
#60000
1!
#70000
0!
#80000
1!
#90000
0!
#100000
1!
#110000
0!
#120000
1!
#130000
0!
#140000
1!
#150000
0!
#160000
1!
#170000
0!
#180000
1!
#190000
0!
#200000
1!
#210000
0!
#220000
1!
#230000
0!
#240000
1!
#250000
0!
#260000
1!
#270000
0!
#280000
1!
#290000
0!
#300000
1!
#310000
0!
#320000
1!
#330000
0!
#340000
1!
#350000
0!
#360000
1!
#370000
0!
#380000
1!
#390000
0!
#400000
1!
1$
#410000
0!
#420000
1!
#430000
0!
#440000
1!
#450000
0!
#460000
1!
#470000
0!
#480000
1!
#490000
0!
#500000
1!
#510000
0!
#520000
1!
#530000
0!
#540000
1!
#550000
0!
#560000
1!
#570000
0!
#580000
1!
#590000
0!
#600000
1!
#610000
0!
#620000
1!
#630000
0!
#640000
1!
#650000
0!
#660000
1!
#670000
0!
#680000
1!
#690000
0!
#700000
1!
#710000
0!
#720000
1!
#730000
0!
#740000
1!
#750000
0!
#760000
1!
#770000
0!
#780000
1!
#790000
0!
#800000
b1 (
b10 '
b1 )
1!
b1 "
b1 #
#810000
0!
#820001
b0 )
0$
b0 "
b0 #
b0 '
b0 (
1!
#830001
0!
#840001
1!
#850001
0!
#860001
1!
#870001
0!
#880001
1!
#890001
0!
#900001
1!
#910001
0!
#920001
1!
#930001
0!
#940001
1!
#950001
0!
#960001
1!
#970001
0!
#980001
1!
#990001
0!
#1000001
1!
#1010001
0!
#1020001
1!
#1030001
0!
#1040001
1!
#1050001
0!
#1060001
1!
#1070001
0!
#1080001
1!
#1090001
0!
#1100001
1!
#1110001
0!
#1120001
1!
#1130001
0!
#1140001
1!
#1150001
0!
#1160001
1!
#1170001
0!
#1180001
1!
#1190001
0!
#1200001
1!
#1210001
0!
#1220001
1!
b1 %
1$
#1230001
0!
#1240001
1!
#1250001
0!
#1260001
1!
#1270001
0!
#1280001
1!
#1290001
0!
#1300001
1!
#1310001
0!
#1320001
1!
#1330001
0!
#1340001
1!
#1350001
0!
#1360001
1!
#1370001
0!
#1380001
1!
#1390001
0!
#1400001
1!
#1410001
0!
#1420001
1!
#1430001
0!
#1440001
1!
#1450001
0!
#1460001
1!
#1470001
0!
#1480001
1!
#1490001
0!
#1500001
1!
#1510001
0!
#1520001
1!
#1530001
0!
#1540001
1!
#1550001
0!
#1560001
1!
#1570001
0!
#1580001
1!
#1590001
0!
#1600001
1!
#1610001
0!
#1620002
0$
b0 %
1!
#1630002
0!
#1640002
1!
#1650002
0!
#1660002
1!
#1670002
0!
#1680002
1!
#1690002
0!
#1700002
1!
#1710002
0!
#1720002
1!
#1730002
0!
#1740002
1!
#1750002
0!
#1760002
1!
#1770002
0!
#1780002
1!
#1790002
0!
#1800002
1!
#1810002
0!
#1820002
1!
#1830002
0!
#1840002
1!
#1850002
0!
#1860002
1!
#1870002
0!
#1880002
1!
#1890002
0!
#1900002
1!
#1910002
0!
#1920002
1!
#1930002
0!
#1940002
1!
#1950002
0!
#1960002
1!
#1970002
0!
#1980002
1!
#1990002
0!
#2000002
1!
#2010002
0!
#2020002
1!
b10 %
1$
#2030002
0!
#2040002
1!
#2050002
0!
#2060002
1!
#2070002
0!
#2080002
1!
#2090002
0!
#2100002
1!
#2110002
0!
#2120002
1!
#2130002
0!
#2140002
1!
#2150002
0!
#2160002
1!
#2170002
0!
#2180002
1!
#2190002
0!
#2200002
1!
#2210002
0!
#2220002
1!
#2230002
0!
#2240002
1!
#2250002
0!
#2260002
1!
#2270002
0!
#2280002
1!
#2290002
0!
#2300002
1!
#2310002
0!
#2320002
1!
#2330002
0!
#2340002
1!
#2350002
0!
#2360002
1!
#2370002
0!
#2380002
1!
#2390002
0!
#2400002
1!
#2410002
0!
#2420002
b110 (
b1100 '
b110 )
1!
b1 #
b110 "
#2430002
0!
#2440002
b10010 '
b1100 (
1!
#2440005
b0 )
0$
b0 %
b0 "
b0 #
b0 '
b0 (
#2450005
0!
#2460005
1!
#2470005
0!
#2480005
1!
#2490005
0!
#2500005
1!
#2510005
0!
#2520005
1!
#2530005
0!
#2540005
1!
#2550005
0!
#2560005
1!
#2570005
0!
#2580005
1!
#2590005
0!
#2600005
1!
#2610005
0!
#2620005
1!
#2630005
0!
#2640005
1!
#2650005
0!
#2660005
1!
#2670005
0!
#2680005
1!
#2690005
0!
#2700005
1!
#2710005
0!
#2720005
1!
#2730005
0!
#2740005
1!
#2750005
0!
#2760005
1!
#2770005
0!
#2780005
1!
#2790005
0!
#2800005
1!
#2810005
0!
#2820005
1!
#2830005
0!
#2840005
1!
b11 %
1$
#2850005
0!
#2860005
1!
#2870005
0!
#2880005
1!
#2890005
0!
#2900005
1!
#2910005
0!
#2920005
1!
#2930005
0!
#2940005
1!
#2950005
0!
#2960005
1!
#2970005
0!
#2980005
1!
#2990005
0!
#3000005
1!
#3010005
0!
#3020005
1!
#3030005
0!
#3040005
1!
#3050005
0!
#3060005
1!
#3070005
0!
#3080005
1!
#3090005
0!
#3100005
1!
#3110005
0!
#3120005
1!
#3130005
0!
#3140005
1!
#3150005
0!
#3160005
1!
#3170005
0!
#3180005
1!
#3190005
0!
#3200005
1!
#3210005
0!
#3220005
1!
#3230005
0!
#3240005
1!
b101 #
b101 "
#3250005
0!
#3260005
1!
#3270005
0!
#3280005
1!
#3280009
b111 #
b111 "
#3290005
0!
#3300005
1!
#3300011
b11 #
b11 "
#3310005
0!
#3320005
1!
#3320013
b111 #
b111 "
#3330005
0!
#3340005
1!
#3350005
0!
#3360005
1!
#3360017
b10 #
b10 "
#3370005
0!
#3380005
1!
#3380019
b1 #
b1 "
#3390005
0!
#3400005
1!
#3400021
b0 #
b0 "
#3410005
0!
#3420005
1!
#3420023
b11 #
b11 "
#3430005
0!
#3440005
1!
#3440025
b1 #
b1 "
#3450005
0!
#3460005
1!
#3460027
b11 #
b11 "
#3470005
0!
#3480005
1!
#3480029
b100 #
b100 "
#3490005
0!
#3500005
1!
#3500031
b1 #
b1 "
#3510005
0!
#3520005
1!
#3520033
b110 #
b110 "
#3530005
0!
#3540005
1!
#3540035
b0 #
b0 "
#3550005
0!
#3560005
1!
#3560037
b11 #
b11 "
#3570005
0!
#3580005
1!
#3580039
b10 #
b10 "
#3590005
0!
#3600005
1!
#3600041
b11 #
b11 "
#3610005
0!
#3620005
1!
#3630005
0!
#3640005
1!
#3640045
b100 #
b100 "
#3650005
0!
#3660005
1!
#3660047
b1 #
b1 "
#3670005
0!
#3680005
1!
#3680049
b100 #
b100 "
#3690005
0!
#3700005
1!
#3700051
b110 #
b110 "
#3710005
0!
#3720005
1!
#3720053
b11 #
b11 "
#3730005
0!
#3740005
1!
#3740055
b100 #
b100 "
#3750005
0!
#3760005
1!
#3770005
0!
#3780005
1!
#3780059
b0 #
b0 "
#3790005
0!
#3800005
1!
#3800061
b101 #
b101 "
#3810005
0!
#3820005
1!
#3820063
b1 #
b1 "
#3830005
0!
#3840005
1!
#3840065
b0 #
b0 "
#3850005
0!
#3860005
1!
#3860067
b10 #
b10 "
#3870005
0!
#3880005
1!
#3890005
0!
#3900005
1!
#3900071
b110 #
b110 "
#3910005
0!
#3920005
1!
#3920073
b111 #
b111 "
#3930005
0!
#3940005
1!
#3940075
b0 #
b0 "
#3950005
0!
#3960005
1!
#3960077
b110 #
b110 "
#3970005
0!
#3980005
1!
#3980079
b100 #
b100 "
#3990005
0!
#4000005
1!
#4000081
b1 #
b1 "
#4010005
0!
#4020005
1!
#4020083
b10 #
b10 "
#4030005
0!
#4040005
1!
#4040085
b110 #
b110 "
#4050005
0!
#4060005
1!
#4060087
b111 #
b111 "
#4070005
0!
#4080005
1!
#4080089
b11 #
b11 "
#4090005
0!
#4100005
1!
#4100091
b0 #
b0 "
#4110005
0!
#4120005
1!
#4120093
b1 #
b1 "
#4130005
0!
#4140005
1!
#4140095
b10 #
b10 "
#4150005
0!
#4160005
1!
#4160097
b110 #
b110 "
#4170005
0!
#4180005
1!
#4180099
b111 #
b111 "
#4190005
0!
#4200005
1!
#4200101
b1 #
b1 "
#4210005
0!
#4220005
1!
#4220103
b0 #
b0 "
#4230005
0!
#4240005
1!
#4240105
b110 #
b110 "
#4250005
0!
#4260005
1!
#4260107
b11 #
b11 "
#4270005
0!
#4280005
1!
#4280109
b101 #
b101 "
#4290005
0!
#4300005
1!
#4300111
b110 #
b110 "
#4310005
0!
#4320005
1!
#4320113
b1 #
b1 "
#4330005
0!
#4340005
1!
#4340115
b100 #
b100 "
#4350005
0!
#4360005
1!
#4360117
b110 #
b110 "
#4370005
0!
#4380005
1!
#4380119
b0 #
b0 "
#4390005
0!
#4400005
1!
#4400121
b110 #
b110 "
#4410005
0!
#4420005
1!
#4420123
b10 #
b10 "
#4430005
0!
#4440005
1!
#4440125
b110 #
b110 "
#4450005
0!
#4460005
1!
#4460127
b101 #
b101 "
#4470005
0!
#4480005
1!
#4490005
0!
#4500005
1!
#4500131
b11 #
b11 "
#4510005
0!
#4520005
1!
#4520133
b111 #
b111 "
#4530005
0!
#4540005
1!
#4540135
b10 #
b10 "
#4550005
0!
#4560005
1!
#4560137
b100 #
b100 "
#4570005
0!
#4580005
1!
#4580139
b111 #
b111 "
#4590005
0!
#4600005
1!
#4610005
0!
#4620005
1!
#4620143
b100 #
b100 "
#4630005
0!
#4640005
1!
#4640145
b101 #
b101 "
#4650005
0!
#4660005
1!
#4660147
b11 #
b11 "
#4670005
0!
#4680005
1!
#4680149
b10 #
b10 "
#4690005
0!
#4700005
1!
#4700151
b110 #
b110 "
#4710005
0!
#4720005
1!
#4720153
b111 #
b111 "
#4730005
0!
#4740005
1!
#4740155
b10 #
b10 "
#4750005
0!
#4760005
1!
#4760157
b111 #
b111 "
#4770005
0!
#4780005
1!
#4790005
0!
#4800005
1!
#4800161
b1 #
b1 "
#4810005
0!
#4820005
1!
#4820163
b111 #
b111 "
#4830005
0!
#4840005
1!
#4840165
b11 #
b11 "
#4850005
0!
#4860005
1!
#4860167
b101 #
b101 "
#4870005
0!
#4880005
1!
#4880169
b111 #
b111 "
#4890005
0!
#4900005
1!
#4900171
b100 #
b100 "
#4910005
0!
#4920005
1!
#4920173
b11 #
b11 "
#4930005
0!
#4940005
1!
#4940175
b10 #
b10 "
#4950005
0!
#4960005
1!
#4970005
0!
#4980005
1!
#4980179
b11 #
b11 "
#4990005
0!
#5000005
1!
#5000181
b101 #
b101 "
#5010005
0!
#5020005
1!
#5020183
b100 #
b100 "
#5030005
0!
#5040005
1!
#5040185
b110 #
b110 "
#5050005
0!
#5060005
1!
#5060187
b101 #
b101 "
#5070005
0!
#5080005
1!
#5090005
0!
#5100005
1!
#5100191
b11 #
b11 "
#5110005
0!
#5120005
1!
#5120193
b100 #
b100 "
#5130005
0!
#5140005
1!
#5140195
b110 #
b110 "
#5150005
0!
#5160005
1!
#5160197
b1 #
b1 "
#5170005
0!
#5180005
1!
#5180199
b101 #
b101 "
#5190005
0!
#5200005
1!
#5210005
0!
#5220005
1!
#5220203
b0 #
b0 "
#5230005
0!
#5240005
1!
#5240205
b110 #
b110 "
#5250005
0!
#5260005
1!
#5260207
b0 #
b0 "
#5270005
0!
#5280005
1!
#5280209
b1 #
b1 "
#5290005
0!
#5300005
1!
#5300211
b110 #
b110 "
#5310005
0!
#5320005
1!
#5320213
b111 #
b111 "
#5330005
0!
#5340005
1!
#5340215
b1 #
b1 "
#5350005
0!
#5360005
1!
#5360217
b110 #
b110 "
#5370005
0!
#5380005
1!
#5380219
b1 #
b1 "
#5390005
0!
#5400005
1!
#5400221
b11 #
b11 "
#5410005
0!
#5420005
1!
#5420223
b1 #
b1 "
#5430005
0!
#5440005
1!
#5440225
b101 #
b101 "
#5450005
0!
#5460005
1!
#5460227
b10 #
b10 "
#5470005
0!
#5480005
1!
#5480229
b1 #
b1 "
#5490005
0!
#5500005
1!
#5500231
b11 #
b11 "
#5510005
0!
#5520005
1!
#5520233
b100 #
b100 "
#5530005
0!
#5540005
1!
#5540235
b101 #
b101 "
#5550005
0!
#5560005
1!
#5560237
b100 #
b100 "
#5570005
0!
#5580005
1!
#5580239
b11 #
b11 "
#5590005
0!
#5600005
1!
#5600241
b10 #
b10 "
#5610005
0!
#5620005
1!
#5620243
b111 #
b111 "
#5630005
0!
#5640005
1!
#5640245
b100 #
b100 "
#5650005
0!
#5660005
1!
#5660247
b110 #
b110 "
#5670005
0!
#5680005
1!
#5680249
b11 #
b11 "
#5690005
0!
#5700005
1!
#5700251
b111 #
b111 "
#5710005
0!
#5720005
1!
#5720253
b1 #
b1 "
#5730005
0!
#5740005
1!
#5740255
b11 #
b11 "
#5750005
0!
#5760005
1!
#5760257
b1 #
b1 "
#5770005
0!
#5780005
1!
#5780259
b110 #
b110 "
