codigos/GP01/ej1/uns_acc.v
//! @title  Unsigned accumulator
//! @author Agustin Matias Ortiz (aortiz@frba.utn.edu.ar)
//! @version 1.0
//! @date 02/09/2022
//!
//! @brief Unsigned accumulator with adder input selection
//! @details Given the extension of the input word that the 
//! statement shows, it is assumed that it is an unsigned 
//! circuit and therefore it is appropriate to speak of Carry and not Overflow.

module uns_acc
(
    output reg [5:0] o_data , //! Acc output
    output           o_carry, //! Carry output

    input      [2:0] i_data2, //! Data imput
    input      [2:0] i_data1, //! Data imput
    input      [1:0] i_sel  , //! Input selection signal

    input            clk    , //! Clock
    input            i_rst_n  //! Asynchronous reset active low
);
//-----------arch-----------

    /*vars*/
    wire [3:0] ext_data1,ext_data2; //!word extention
    reg  [3:0] sel_out;             //!input MUX
    wire [6:0] adder_out;           //!next state adder output

    //!Mux of selection of the input data to accumulate
    always @(*) begin :input_selector
        case (i_sel)
            2'b00: 
                    sel_out = {1'b0,i_data2};
            2'b01: 
                    sel_out = i_data2 + i_data1;
            2'b10: 
                    sel_out = {1'b0,i_data1};
            2'b11: 
                    sel_out = {3{1'b0}};
            default: 
                    sel_out = {3{1'b0}};
        endcase
    end

    //!next state adder
    assign adder_out = o_data + {2'b00,sel_out};

    //!accumulator register
    always @(posedge clk or negedge i_rst_n) begin:accumulator
        if(! i_rst_n) begin
            o_data <= {5{1'b0}};
        end
        else begin 
            o_data <= adder_out[5:0];
        end
    end

    assign o_carry = adder_out[6];

endmodule

codigos/GP01/ej1/uns_acc.vcd
$date
	Wed Sep 21 00:25:26 2022
$end
$version
	Icarus Verilog
$end
$timescale
	1ps
$end
$scope module uns_acc $end
$var wire 1 ! clk $end
$var wire 3 " i_data1 [2:0] $end
$var wire 3 # i_data2 [2:0] $end
$var wire 1 $ i_rst_n $end
$var wire 2 % i_sel [1:0] $end
$var wire 1 & o_carry $end
$var wire 7 ' adder_out [6:0] $end
$var reg 6 ( o_data [5:0] $end
$var reg 4 ) sel_out [3:0] $end
$scope begin accumulator $end
$upscope $end
$scope begin input_selector $end
$upscope $end
$upscope $end
$enddefinitions $end
#0
$dumpvars
b0 )
b0 (
b0 '
0&
b0 %
0$
b0 #
b0 "
1!
$end
#10000
0!
#20000
1!
#30000
0!
#40000
1!
#50000
0!
#60000
1!
#70000
0!
#80000
1!
#90000
0!
#100000
1!
#110000
0!
#120000
1!
#130000
0!
#140000
1!
#150000
0!
#160000
1!
#170000
0!
#180000
1!
#190000
0!
#200000
1!
#210000
0!
#220000
1!
#230000
0!
#240000
1!
#250000
0!
#260000
1!
#270000
0!
#280000
1!
#290000
0!
#300000
1!
#310000
0!
#320000
1!
#330000
0!
#340000
1!
#350000
0!
#360000
1!
#370000
0!
#380000
1!
#390000
0!
#400000
1$
1!
#410000
0!
#420000
1!
#430000
0!
#440000
1!
#450000
0!
#460000
1!
#470000
0!
#480000
1!
#490000
0!
#500000
1!
#510000
0!
#520000
1!
#530000
0!
#540000
1!
#550000
0!
#560000
1!
#570000
0!
#580000
1!
#590000
0!
#600000
1!
#610000
0!
#620000
1!
#630000
0!
#640000
1!
#650000
0!
#660000
1!
#670000
0!
#680000
1!
#690000
0!
#700000
1!
#710000
0!
#720000
1!
#730000
0!
#740000
1!
#750000
0!
#760000
1!
#770000
0!
#780000
1!
#790000
0!
#800000
b1 '
b1 )
b1 #
b111 "
1!
#810000
0!
#820000
b10 '
b1 (
b100 "
1!
#830000
0!
#840000
b11 '
b10 (
b10 "
1!
#850000
0!
#860000
b100 '
b11 (
b1 "
1!
#870000
0!
#880000
b101 '
b100 (
b11 "
1!
#890000
0!
#900000
b110 '
b101 (
b100 "
1!
#910000
0!
#920000
b111 '
b110 (
b101 "
1!
#930000
0!
#940000
b1000 '
b111 (
b1 "
1!
#950000
0!
#960000
b1001 '
b1000 (
1!
#970000
0!
#980000
b1010 '
b1001 (
b111 "
1!
#990000
0!
#1000000
b1011 '
b1010 (
b100 "
1!
#1010000
0!
#1020000
b1100 '
b1011 (
b101 "
1!
#1030000
0!
#1040000
b1101 '
b1100 (
b110 "
1!
#1050000
0!
#1060000
b1110 '
b1101 (
b101 "
1!
#1070000
0!
#1080000
b1111 '
b1110 (
b0 "
1!
#1090000
0!
#1100000
b10000 '
b1111 (
b110 "
1!
#1110000
0!
#1120000
b10001 '
b10000 (
b101 "
1!
#1130000
0!
#1140000
b10010 '
b10001 (
b1 "
1!
#1150000
0!
#1160000
b10011 '
b10010 (
b0 "
1!
#1170000
0!
#1180000
b10100 '
b10011 (
b11 "
1!
#1190000
0!
#1200000
b10101 '
b10100 (
b111 "
1!
#1210000
0!
#1220000
b10110 '
b10101 (
1!
#1230000
0!
#1240000
b10111 '
b10110 (
b11 "
1!
#1250000
0!
#1260000
b11000 '
b10111 (
b0 "
1!
#1270000
0!
#1280000
b11001 '
b11000 (
b11 "
1!
#1290000
0!
#1300000
b11010 '
b11001 (
1!
#1310000
0!
#1320000
b11011 '
b11010 (
b101 "
1!
#1330000
0!
#1340000
b11100 '
b11011 (
b0 "
1!
#1350000
0!
#1360000
b11101 '
b11100 (
1!
#1370000
0!
#1380000
b11110 '
b11101 (
b100 "
1!
#1390000
0!
#1400000
b11111 '
b11110 (
b111 "
1!
#1410000
0!
#1420000
b100000 '
b11111 (
1!
#1430000
0!
#1440000
b100001 '
b100000 (
b10 "
1!
#1450000
0!
#1460000
b100010 '
b100001 (
b100 "
1!
#1470000
0!
#1480000
b100011 '
b100010 (
b110 "
1!
#1490000
0!
#1500000
b100100 '
b100011 (
b1 "
1!
#1510000
0!
#1520000
b100101 '
b100100 (
b100 "
1!
#1530000
0!
#1540000
b100110 '
b100101 (
1!
#1550000
0!
#1560000
b100111 '
b100110 (
b10 "
1!
#1570000
0!
#1580000
b101000 '
b100111 (
b111 "
1!
#1590000
0!
#1600000
b101001 '
b101000 (
b10 "
1!
#1610000
0!
#1620000
b101010 '
b101001 (
b11 "
1!
#1630000
0!
#1640000
b101011 '
b101010 (
b111 "
1!
#1650000
0!
#1660000
b101100 '
b101011 (
b100 "
1!
#1670000
0!
#1680000
b101101 '
b101100 (
1!
#1690000
0!
#1700000
b101110 '
b101101 (
b11 "
1!
#1710000
0!
#1720000
b101111 '
b101110 (
1!
#1730000
0!
#1740000
b110000 '
b101111 (
1!
#1750000
0!
#1760000
b110001 '
b110000 (
b111 "
1!
#1770000
0!
#1780000
b110010 '
b110001 (
b0 "
1!
#1790000
0!
#1800000
b110011 '
b110010 (
b110 "
1!
#1810000
0!
#1820000
b110100 '
b110011 (
b10 "
1!
#1830000
0!
#1840000
b110101 '
b110100 (
b0 "
1!
#1850000
0!
#1860000
b110110 '
b110101 (
b111 "
1!
#1870000
0!
#1880000
b110111 '
b110110 (
b1 "
1!
#1890000
0!
#1900000
b111000 '
b110111 (
b0 "
1!
#1910000
0!
#1920000
b111001 '
b111000 (
b1 "
1!
#1930000
0!
#1940000
b111010 '
b111001 (
b101 "
1!
#1950000
0!
#1960000
b111011 '
b111010 (
b110 "
1!
#1970000
0!
#1980000
b111100 '
b111011 (
b11 "
1!
#1990000
0!
#2000000
b111101 '
b111100 (
b1 "
1!
#2010000
0!
#2020000
b111110 '
b111101 (
1!
#2030000
0!
#2040000
b111111 '
b111110 (
b101 "
1!
#2050000
0!
#2060000
1&
b1000000 '
b111111 (
b111 "
1!
#2070000
0!
#2080000
0&
b1 '
b0 (
b11 "
1!
#2090000
0!
#2100000
b10 '
b1 (
1!
#2110000
0!
#2120000
b11 '
b10 (
b101 "
1!
#2130000
0!
#2140000
b100 '
b11 (
b111 "
1!
#2150000
0!
#2160000
b101 '
b100 (
b101 "
1!
#2170000
0!
#2180000
b110 '
b101 (
b0 "
1!
#2190000
0!
#2200000
b111 '
b110 (
b100 "
1!
#2210000
0!
#2220000
b1000 '
b111 (
b111 "
1!
#2230000
0!
#2240000
b1001 '
b1000 (
b110 "
1!
#2250000
0!
#2260000
b1010 '
b1001 (
b11 "
1!
#2270000
0!
#2280000
b1011 '
b1010 (
1!
#2290000
0!
#2300000
b1100 '
b1011 (
1!
#2310000
0!
#2320000
b1101 '
b1100 (
b101 "
1!
#2330000
0!
#2340000
b1110 '
b1101 (
b111 "
1!
#2350000
0!
#2360000
b1111 '
b1110 (
1!
#2370000
0!
#2380000
b10000 '
b1111 (
b1 "
1!
#2390000
0!
#2400000
b10001 '
b10000 (
b0 "
1!
#2410000
0!
#2420000
b10010 '
b10001 (
b110 "
1!
#2430000
0!
#2440000
b10011 '
b10010 (
b1 "
1!
#2450000
0!
#2460000
b10100 '
b10011 (
b111 "
1!
#2470000
0!
#2480000
b10101 '
b10100 (
1!
#2490000
0!
#2500000
b10110 '
b10101 (
b0 "
1!
#2510000
0!
#2520000
b10111 '
b10110 (
b11 "
1!
#2530000
0!
#2540000
b11000 '
b10111 (
1!
#2550000
0!
#2560000
b11001 '
b11000 (
b110 "
1!
#2570000
0!
#2580000
b11010 '
b11001 (
b111 "
1!
#2590000
0!
#2600000
b11011 '
b11010 (
1!
#2610000
0!
#2620000
b11100 '
b11011 (
b1 "
1!
#2630000
0!
#2640000
b11101 '
b11100 (
b0 "
1!
#2650000
0!
#2660000
b11110 '
b11101 (
b111 "
1!
#2670000
0!
#2680000
b11111 '
b11110 (
b110 "
1!
#2690000
0!
#2700000
b100000 '
b11111 (
b111 "
1!
#2710000
0!
#2720000
b100001 '
b100000 (
b0 "
1!
#2730000
0!
#2740000
b100010 '
b100001 (
b100 "
1!
#2750000
0!
#2760000
b100011 '
b100010 (
1!
#2770000
0!
#2780000
b100100 '
b100011 (
1!
#2790000
0!
#2800000
b100101 '
b100100 (
b111 "
1!
#2810000
0!
#2820000
b100110 '
b100101 (
1!
#2830000
0!
#2840000
b100111 '
b100110 (
b11 "
1!
#2850000
0!
#2860000
b101000 '
b100111 (
b1 "
1!
#2870000
0!
#2880000
b101001 '
b101000 (
1!
#2890000
0!
#2900000
b101010 '
b101001 (
b11 "
1!
#2910000
0!
#2920000
b101011 '
b101010 (
1!
#2930000
0!
#2940000
b101100 '
b101011 (
b100 "
1!
#2950000
0!
#2960000
b101101 '
b101100 (
b111 "
1!
#2970000
0!
#2980000
b101110 '
b101101 (
b0 "
1!
#2990000
0!
#3000000
b101111 '
b101110 (
b110 "
1!
#3010000
0!
#3020000
b110000 '
b101111 (
1!
#3030000
0!
#3040000
b110001 '
b110000 (
1!
#3050000
0!
#3060000
b110010 '
b110001 (
b111 "
1!
#3070000
0!
#3080000
b110011 '
b110010 (
1!
#3090000
0!
#3100000
b110100 '
b110011 (
b101 "
1!
#3110000
0!
#3120000
b110101 '
b110100 (
1!
#3130000
0!
#3140000
b110110 '
b110101 (
b11 "
1!
#3150000
0!
#3160000
b110111 '
b110110 (
b100 "
1!
#3170000
0!
#3180000
b111000 '
b110111 (
b110 "
1!
#3190000
0!
#3200000
b111001 '
b111000 (
b100 "
1!
#3210000
0!
#3220000
b111010 '
b111001 (
b101 "
1!
#3230000
0!
#3240000
b111011 '
b111010 (
1!
#3250000
0!
#3260000
b111100 '
b111011 (
b1 "
1!
#3270000
0!
#3280000
b111101 '
b111100 (
b0 "
1!
#3290000
0!
#3300000
b111110 '
b111101 (
b10 "
1!
#3310000
0!
#3320000
b111111 '
b111110 (
b0 "
1!
#3330000
0!
#3340000
1&
b1000000 '
b111111 (
b101 "
1!
#3350000
0!
#3360000
0&
b1 '
b0 (
1!
#3370000
0!
#3380001
b0 '
b0 )
1!
b0 #
b0 "
0$
#3390001
0!
#3400001
1!
#3410001
0!
#3420001
1!
#3430001
0!
#3440001
1!
#3450001
0!
#3460001
1!
#3470001
0!
#3480001
1!
#3490001
0!
#3500001
1!
#3510001
0!
#3520001
1!
#3530001
0!
#3540001
1!
#3550001
0!
#3560001
1!
#3570001
0!
#3580001
1!
#3590001
0!
#3600001
1!
#3610001
0!
#3620001
1!
#3630001
0!
#3640001
1!
#3650001
0!
#3660001
1!
#3670001
0!
#3680001
1!
#3690001
0!
#3700001
1!
#3710001
0!
#3720001
1!
#3730001
0!
#3740001
1!
#3750001
0!
#3760001
1!
#3770001
0!
#3780001
1$
b1 %
1!
#3790001
0!
#3800001
1!
#3810001
0!
#3820001
1!
#3830001
0!
#3840001
1!
#3850001
0!
#3860001
1!
#3870001
0!
#3880001
1!
#3890001
0!
#3900001
1!
#3910001
0!
#3920001
1!
#3930001
0!
#3940001
1!
#3950001
0!
#3960001
1!
#3970001
0!
#3980001
1!
#3990001
0!
#4000001
1!
#4010001
0!
#4020001
1!
#4030001
0!
#4040001
1!
#4050001
0!
#4060001
1!
#4070001
0!
#4080001
1!
#4090001
0!
#4100001
1!
#4110001
0!
#4120001
1!
#4130001
0!
#4140001
1!
#4150001
0!
#4160001
1!
#4170001
0!
#4180002
1!
b0 %
0$
#4190002
0!
#4200002
1!
#4210002
0!
#4220002
1!
#4230002
0!
#4240002
1!
#4250002
0!
#4260002
1!
#4270002
0!
#4280002
1!
#4290002
0!
#4300002
1!
#4310002
0!
#4320002
1!
#4330002
0!
#4340002
1!
#4350002
0!
#4360002
1!
#4370002
0!
#4380002
1!
#4390002
0!
#4400002
1!
#4410002
0!
#4420002
1!
#4430002
0!
#4440002
1!
#4450002
0!
#4460002
1!
#4470002
0!
#4480002
1!
#4490002
0!
#4500002
1!
#4510002
0!
#4520002
1!
#4530002
0!
#4540002
1!
#4550002
0!
#4560002
1!
#4570002
0!
#4580002
1$
b10 %
1!
#4590002
0!
#4600002
1!
#4610002
0!
#4620002
1!
#4630002
0!
#4640002
1!
#4650002
0!
#4660002
1!
#4670002
0!
#4680002
1!
#4690002
0!
#4700002
1!
#4710002
0!
#4720002
1!
#4730002
0!
#4740002
1!
#4750002
0!
#4760002
1!
#4770002
0!
#4780002
1!
#4790002
0!
#4800002
1!
#4810002
0!
#4820002
1!
#4830002
0!
#4840002
1!
#4850002
0!
#4860002
1!
#4870002
0!
#4880002
1!
#4890002
0!
#4900002
1!
#4910002
0!
#4920002
1!
#4930002
0!
#4940002
1!
#4950002
0!
#4960002
1!
#4970002
0!
#4980002
b101 '
b101 )
b101 "
b1 #
1!
#4990002
0!
#5000002
b1010 '
b101 (
1!
#5000004
b111 '
b10 )
b10 "
#5010002
0!
#5020002
b1001 '
b111 (
1!
#5020006
b1101 '
b110 )
b110 "
#5030002
0!
#5040002
b10011 '
b1101 (
1!
#5040008
b1101 '
b0 )
b0 "
#5050002
0!
#5060002
1!
#5070002
0!
#5080002
1!
#5080012
b1110 '
b1 )
b1 "
#5090002
0!
#5100002
b1111 '
b1110 (
1!
#5100014
b10000 '
b10 )
b10 "
#5110002
0!
#5120002
b10010 '
b10000 (
1!
#5120016
b10100 '
b100 )
b100 "
#5130002
0!
#5140002
b11000 '
b10100 (
1!
#5140018
b10110 '
b10 )
b10 "
#5150002
0!
#5160002
b11000 '
b10110 (
1!
#5160020
b10110 '
b0 )
b0 "
#5170002
0!
#5180002
1!
#5180022
b11011 '
b101 )
b101 "
#5190002
0!
#5200002
b100000 '
b11011 (
1!
#5200024
b11101 '
b10 )
b10 "
#5210002
0!
#5220002
b11111 '
b11101 (
1!
#5220026
b11101 '
b0 )
b0 "
#5230002
0!
#5240002
1!
#5240028
b100011 '
b110 )
b110 "
#5250002
0!
#5260002
b101001 '
b100011 (
1!
#5260030
b100111 '
b100 )
b100 "
#5270002
0!
#5280002
b101011 '
b100111 (
1!
#5280032
b101010 '
b11 )
b11 "
#5290002
0!
#5300002
b101101 '
b101010 (
1!
#5300034
b110000 '
b110 )
b110 "
#5310002
0!
#5320002
b110110 '
b110000 (
1!
#5330002
0!
#5340002
b111100 '
b110110 (
1!
#5340038
b111011 '
b101 )
b101 "
#5350002
0!
#5360002
1&
b1000000 '
b111011 (
1!
#5360040
0&
b111101 '
b10 )
b10 "
#5370002
0!
#5380002
b111111 '
b111101 (
1!
#5380042
1&
b1000000 '
b11 )
b11 "
#5390002
0!
#5400002
0&
b11 '
b0 (
1!
#5400044
b100 '
b100 )
b100 "
#5410002
0!
#5420002
b1000 '
b100 (
1!
#5420046
b101 '
b1 )
b1 "
#5430002
0!
#5440002
b110 '
b101 (
1!
#5440048
b101 '
b0 )
b0 "
#5450002
0!
#5460002
1!
#5460050
b1010 '
b101 )
b101 "
#5470002
0!
#5480002
b1111 '
b1010 (
1!
#5480052
b1010 '
b0 )
b0 "
#5490002
0!
#5500002
1!
#5500054
b10000 '
b110 )
b110 "
#5510002
0!
#5520002
b10110 '
b10000 (
1!
#5520056
b10011 '
b11 )
b11 "
#5530002
0!
#5540002
b10110 '
b10011 (
1!
#5540058
b10100 '
b1 )
b1 "
#5550002
0!
#5560002
b10101 '
b10100 (
1!
#5560060
b11000 '
b100 )
b100 "
#5570002
0!
#5580002
b11100 '
b11000 (
1!
#5580062
b11001 '
b1 )
b1 "
#5590002
0!
#5600002
b11010 '
b11001 (
1!
#5600064
b11110 '
b101 )
b101 "
#5610002
0!
#5620002
b100011 '
b11110 (
1!
#5620066
b100101 '
b111 )
b111 "
#5630002
0!
#5640002
b101100 '
b100101 (
1!
#5640068
b101011 '
b110 )
b110 "
#5650002
0!
#5660002
b110001 '
b101011 (
1!
#5660070
b101110 '
b11 )
b11 "
#5670002
0!
#5680002
b110001 '
b101110 (
1!
#5680072
b110100 '
b110 )
b110 "
#5690002
0!
#5700002
b111010 '
b110100 (
1!
#5700074
b110101 '
b1 )
b1 "
#5710002
0!
#5720002
b110110 '
b110101 (
1!
#5720076
b111100 '
b111 )
b111 "
#5730002
0!
#5740002
1&
b1000011 '
b111100 (
1!
#5740078
b1000000 '
b100 )
b100 "
#5750002
0!
#5760002
0&
b100 '
b0 (
1!
#5770002
0!
#5780002
b1000 '
b100 (
1!
#5780082
b100 '
b0 )
b0 "
#5790002
0!
#5800002
1!
#5800084
b111 '
b11 )
b11 "
#5810002
0!
#5820002
b1010 '
b111 (
1!
#5830002
0!
#5840002
b1101 '
b1010 (
1!
#5840088
b10001 '
b111 )
b111 "
#5850002
0!
#5860002
b11000 '
b10001 (
1!
#5860090
b10111 '
b110 )
b110 "
#5870002
0!
#5880002
b11101 '
b10111 (
1!
#5880092
b11001 '
b10 )
b10 "
#5890002
0!
#5900002
b11011 '
b11001 (
1!
#5900094
b11101 '
b100 )
b100 "
#5910002
0!
#5920002
b100001 '
b11101 (
1!
#5920096
b11110 '
b1 )
b1 "
#5930002
0!
#5940002
b11111 '
b11110 (
1!
#5940098
b100001 '
b11 )
b11 "
#5950002
0!
#5960002
b100100 '
b100001 (
1!
#5960100
b100111 '
b110 )
b110 "
#5970002
0!
#5980002
b101101 '
b100111 (
1!
#5990002
0!
#6000002
b110011 '
b101101 (
1!
#6000104
b101101 '
b0 )
b0 "
#6010002
0!
#6020002
1!
#6020106
b110010 '
b101 )
b101 "
#6030002
0!
#6040002
b110111 '
b110010 (
1!
#6040108
b111000 '
b110 )
b110 "
#6050002
0!
#6060002
b111110 '
b111000 (
1!
#6060110
b111001 '
b1 )
b1 "
#6070002
0!
#6080002
b111010 '
b111001 (
1!
#6080112
b111001 '
b0 )
b0 "
#6090002
0!
#6100002
1!
#6100114
b111111 '
b110 )
b110 "
#6110002
0!
#6120002
1&
b1000101 '
b111111 (
1!
#6120116
b1000110 '
b111 )
b111 "
#6130002
0!
#6140002
0&
b1101 '
b110 (
1!
#6140118
b1000 '
b10 )
b10 "
#6150002
0!
#6160002
b1010 '
b1000 (
1!
#6160120
b1100 '
b100 )
b100 "
#6170002
0!
#6180002
b10000 '
b1100 (
1!
#6180122
b1100 '
b0 )
b0 "
#6190002
0!
#6200002
1!
#6200124
b10010 '
b110 )
b110 "
#6210002
0!
#6220002
b11000 '
b10010 (
1!
#6220126
b10010 '
b0 )
b0 "
#6230002
0!
#6240002
1!
#6240128
b10111 '
b101 )
b101 "
#6250002
0!
#6260002
b11100 '
b10111 (
1!
#6260130
b11101 '
b110 )
b110 "
#6270002
0!
#6280002
b100011 '
b11101 (
1!
#6280132
b11101 '
b0 )
b0 "
#6290002
0!
#6300002
1!
#6310002
0!
#6320002
1!
#6320136
b11111 '
b10 )
b10 "
#6330002
0!
#6340002
b100001 '
b11111 (
1!
#6340138
b100101 '
b110 )
b110 "
#6350002
0!
#6360002
b101011 '
b100101 (
1!
#6360140
b101000 '
b11 )
b11 "
#6370002
0!
#6380002
b101011 '
b101000 (
1!
#6380142
b101001 '
b1 )
b1 "
#6390002
0!
#6400002
b101010 '
b101001 (
1!
#6400144
b101001 '
b0 )
b0 "
#6410002
0!
#6420002
1!
#6420146
b110000 '
b111 )
b111 "
#6430002
0!
#6440002
b110111 '
b110000 (
1!
#6440148
b110000 '
b0 )
b0 "
#6450002
0!
#6460002
1!
#6460150
b110111 '
b111 )
b111 "
#6470002
0!
#6480002
b111110 '
b110111 (
1!
#6480152
b110111 '
b0 )
b0 "
#6490002
0!
#6500002
1!
#6500154
b111101 '
b110 )
b110 "
#6510002
0!
#6520002
1&
b1000011 '
b111101 (
1!
#6520156
0&
b111110 '
b1 )
b1 "
#6530002
0!
#6540002
b111111 '
b111110 (
1!
#6540158
1&
b1000011 '
b101 )
b101 "
#6550002
0!
#6560002
0&
b1000 '
b11 (
1!
#6560160
b1001 '
b110 )
b110 "
#6570002
0!
#6580002
b1111 '
b1001 (
1!
#6580162
b1101 '
b100 )
b100 "
#6590002
0!
#6600002
b10001 '
b1101 (
1!
#6600164
b10011 '
b110 )
b110 "
#6610002
0!
#6620002
b11001 '
b10011 (
1!
#6620166
b10011 '
b0 )
b0 "
#6630002
0!
#6640002
1!
#6650002
0!
#6660002
1!
#6660170
b11010 '
b111 )
b111 "
#6670002
0!
#6680002
b100001 '
b11010 (
1!
#6690002
0!
#6700002
b101000 '
b100001 (
1!
#6700174
b100010 '
b1 )
b1 "
#6710002
0!
#6720002
b100011 '
b100010 (
1!
#6720176
b100110 '
b100 )
b100 "
#6730002
0!
#6740002
b101010 '
b100110 (
1!
#6740178
b101001 '
b11 )
b11 "
#6750002
0!
#6760002
b101100 '
b101001 (
1!
#6760180
b110000 '
b111 )
b111 "
#6770002
0!
#6780002
b110111 '
b110000 (
1!
#6780182
b110100 '
b100 )
b100 "
#6790002
0!
#6800002
b111000 '
b110100 (
1!
#6800184
b111010 '
b110 )
b110 "
#6810002
0!
#6820002
1&
b1000000 '
b111010 (
1!
#6820186
0&
b111100 '
b10 )
b10 "
#6830002
0!
#6840002
b111110 '
b111100 (
1!
#6840188
1&
b1000011 '
b111 )
b111 "
#6850002
0!
#6860002
0&
b1010 '
b11 (
1!
#6860190
b101 '
b10 )
b10 "
#6870002
0!
#6880002
b111 '
b101 (
1!
#6880192
b1001 '
b100 )
b100 "
#6890002
0!
#6900002
b1101 '
b1001 (
1!
#6900194
b1111 '
b110 )
b110 "
#6910002
0!
#6920002
b10101 '
b1111 (
1!
#6920196
b10010 '
b11 )
b11 "
#6930002
0!
#6940002
b10101 '
b10010 (
1!
#6940198
b11000 '
b110 )
b110 "
#6950002
0!
#6960002
b11110 '
b11000 (
1!
#6960200
b11010 '
b10 )
b10 "
#6970002
0!
#6980002
b11100 '
b11010 (
1!
#6980202
b11110 '
b100 )
b100 "
#6990002
0!
#7000002
b100010 '
b11110 (
1!
#7000204
b100011 '
b101 )
b101 "
#7010002
0!
#7020002
b101000 '
b100011 (
1!
#7030002
0!
#7040002
b101101 '
b101000 (
1!
#7040208
b101010 '
b10 )
b10 "
#7050002
0!
#7060002
b101100 '
b101010 (
1!
#7070002
0!
#7080002
b101110 '
b101100 (
1!
#7080212
b101111 '
b11 )
b11 "
#7090002
0!
#7100002
b110010 '
b101111 (
1!
#7100214
b110110 '
b111 )
b111 "
#7110002
0!
#7120002
b111101 '
b110110 (
1!
#7120216
b110110 '
b0 )
b0 "
#7130002
0!
#7140002
1!
#7140218
b111001 '
b11 )
b11 "
#7150002
0!
#7160002
b111100 '
b111001 (
1!
#7170002
0!
#7180002
b111111 '
b111100 (
1!
#7180222
b111110 '
b10 )
b10 "
#7190002
0!
#7200002
1&
b1000000 '
b111110 (
1!
#7210002
0!
#7220002
0&
b10 '
b0 (
1!
#7220226
b111 '
b111 )
b111 "
#7230002
0!
#7240002
b1110 '
b111 (
1!
#7240228
b1000 '
b1 )
b1 "
#7250002
0!
#7260002
b1001 '
b1000 (
1!
#7260230
b1111 '
b111 )
b111 "
#7270002
0!
#7280002
b10110 '
b1111 (
1!
#7280232
b10011 '
b100 )
b100 "
#7290002
0!
#7300002
b10111 '
b10011 (
1!
#7300234
b10100 '
b1 )
b1 "
#7310002
0!
#7320002
b10101 '
b10100 (
1!
#7320236
b11011 '
b111 )
b111 "
#7330002
0!
#7340002
b100010 '
b11011 (
1!
#7340238
b11110 '
b11 )
b11 "
#7350002
0!
#7360002
b100001 '
b11110 (
1!
#7360240
b100010 '
b100 )
b100 "
#7370002
0!
#7380002
b100110 '
b100010 (
1!
#7380242
b100011 '
b1 )
b1 "
#7390002
0!
#7400002
b100100 '
b100011 (
1!
#7400244
b101000 '
b101 )
b101 "
#7410002
0!
#7420002
b101101 '
b101000 (
1!
#7430002
0!
#7440002
b110010 '
b101101 (
1!
#7450002
0!
#7460002
b110111 '
b110010 (
1!
#7460250
b111000 '
b110 )
b110 "
#7470002
0!
#7480002
b111110 '
b111000 (
1!
#7480252
b111010 '
b10 )
b10 "
#7490002
0!
#7500002
b111100 '
b111010 (
1!
#7500254
1&
b1000001 '
b111 )
b111 "
#7510002
0!
#7520002
0&
b1000 '
b1 (
1!
#7520256
b100 '
b11 )
b11 "
#7530002
0!
#7540002
b111 '
b100 (
1!
#7540259
b0 )
b0 '
b0 (
b0 #
b0 "
b0 %
0$
#7550259
0!
#7560259
1!
#7570259
0!
#7580259
1!
#7590259
0!
#7600259
1!
#7610259
0!
#7620259
1!
#7630259
0!
#7640259
1!
#7650259
0!
#7660259
1!
#7670259
0!
#7680259
1!
#7690259
0!
#7700259
1!
#7710259
0!
#7720259
1!
#7730259
0!
#7740259
1!
#7750259
0!
#7760259
1!
#7770259
0!
#7780259
1!
#7790259
0!
#7800259
1!
#7810259
0!
#7820259
1!
#7830259
0!
#7840259
1!
#7850259
0!
#7860259
1!
#7870259
0!
#7880259
1!
#7890259
0!
#7900259
1!
#7910259
0!
#7920259
1!
#7930259
0!
#7940259
1$
b11 %
1!
