codigos/GP01/ej1/uns_acc.v
//! @title  Unsigned accumulator
//! @author Agustin Matias Ortiz (aortiz@frba.utn.edu.ar)
//! @version 1.0
//! @date 02/09/2022
//!
//! @brief Unsigned accumulator with adder input selection
//! @details Given the extension of the input word that the 
//! statement shows, it is assumed that it is an unsigned 
//! circuit and therefore it is appropriate to speak of Carry and not Overflow.
`define COCOTB_SIM 1

module uns_acc
(
    output reg [5:0] o_data , //! Acc output
    output           o_carry, //! Carry output

    input      [2:0] i_data2, //! Data imput
    input      [2:0] i_data1, //! Data imput
    input      [1:0] i_sel  , //! Input selection signal

    input            clk    , //! Clock
    input            i_rst_n  //! Asynchronous reset active low
);
//-----------arch-----------

    /*vars*/
    wire [3:0] ext_data1,ext_data2; //!word extention
    reg  [3:0] sel_out;             //!input MUX
    wire [6:0] adder_out;           //!next state adder output

    //!Mux of selection of the input data to accumulate
    always @(*) begin :input_selector
        case (i_sel)
            2'b00: 
                    sel_out = {1'b0,i_data2};
            2'b01: 
                    sel_out = i_data2 + i_data1;
            2'b10: 
                    sel_out = {1'b0,i_data1};
            2'b11: 
                    sel_out = {3{1'b0}};
            default: 
                    sel_out = {3{1'b0}};
        endcase
    end

    //!next state adder
    assign adder_out = o_data + {2'b00,sel_out};

    //!accumulator register
    always @(posedge clk or negedge i_rst_n) begin:accumulator
        if(! i_rst_n) begin
            o_data <= {5{1'b0}};
        end
        else begin 
            o_data <= adder_out[5:0];
        end
    end

    assign o_carry = adder_out[6];

    /* for cocotb sim*/
    `ifdef COCOTB_SIM
    initial begin
      $dumpfile ("uns_acc.vcd");
      $dumpvars (0, uns_acc);
      #1;
    end
    `endif

endmodule

codigos/GP01/ej1/uns_acc.vcd
$date
	Wed Sep 21 00:05:16 2022
$end
$version
	Icarus Verilog
$end
$timescale
	1ps
$end
$scope module uns_acc $end
$var wire 1 ! clk $end
$var wire 3 " i_data1 [2:0] $end
$var wire 3 # i_data2 [2:0] $end
$var wire 1 $ i_rst_n $end
$var wire 2 % i_sel [1:0] $end
$var wire 1 & o_carry $end
$var wire 7 ' adder_out [6:0] $end
$var reg 6 ( o_data [5:0] $end
$var reg 4 ) sel_out [3:0] $end
$scope begin accumulator $end
$upscope $end
$scope begin input_selector $end
$upscope $end
$upscope $end
$enddefinitions $end
#0
$dumpvars
b0 )
b0 (
b0 '
0&
b0 %
0$
b0 #
b0 "
1!
$end
#10000
0!
#20000
1!
#30000
0!
#40000
1!
#50000
0!
#60000
1!
#70000
0!
#80000
1!
#90000
0!
#100000
1!
#110000
0!
#120000
1!
#130000
0!
#140000
1!
#150000
0!
#160000
1!
#170000
0!
#180000
1!
#190000
0!
#200000
1!
#210000
0!
#220000
1!
#230000
0!
#240000
1!
#250000
0!
#260000
1!
#270000
0!
#280000
1!
#290000
0!
#300000
1!
#310000
0!
#320000
1!
#330000
0!
#340000
1!
#350000
0!
#360000
1!
#370000
0!
#380000
1!
#390000
0!
#400000
1$
1!
#410000
0!
#420000
1!
#430000
0!
#440000
1!
#450000
0!
#460000
1!
#470000
0!
#480000
1!
#490000
0!
#500000
1!
#510000
0!
#520000
1!
#530000
0!
#540000
1!
#550000
0!
#560000
1!
#570000
0!
#580000
1!
#590000
0!
#600000
1!
#610000
0!
#620000
1!
#630000
0!
#640000
1!
#650000
0!
#660000
1!
#670000
0!
#680000
1!
#690000
0!
#700000
1!
#710000
0!
#720000
1!
#730000
0!
#740000
1!
#750000
0!
#760000
1!
#770000
0!
#780000
1!
#790000
0!
#800000
b1 '
b1 )
b1 #
b11 "
1!
#810000
0!
#820000
b10 '
b1 (
b10 "
1!
#830000
0!
#840000
b11 '
b10 (
b0 "
1!
#850000
0!
#860000
b100 '
b11 (
b111 "
1!
#870000
0!
#880000
b101 '
b100 (
b101 "
1!
#890000
0!
#900000
b110 '
b101 (
b111 "
1!
#910000
0!
#920000
b111 '
b110 (
b101 "
1!
#930000
0!
#940000
b1000 '
b111 (
b0 "
1!
#950000
0!
#960000
b1001 '
b1000 (
1!
#970000
0!
#980000
b1010 '
b1001 (
b11 "
1!
#990000
0!
#1000000
b1011 '
b1010 (
b101 "
1!
#1010000
0!
#1020000
b1100 '
b1011 (
b110 "
1!
#1030000
0!
#1040000
b1101 '
b1100 (
b111 "
1!
#1050000
0!
#1060000
b1110 '
b1101 (
b1 "
1!
#1070000
0!
#1080000
b1111 '
b1110 (
1!
#1090000
0!
#1100000
b10000 '
b1111 (
b111 "
1!
#1110000
0!
#1120000
b10001 '
b10000 (
b101 "
1!
#1130000
0!
#1140000
b10010 '
b10001 (
b0 "
1!
#1150000
0!
#1160000
b10011 '
b10010 (
b11 "
1!
#1170000
0!
#1180000
b10100 '
b10011 (
b100 "
1!
#1190000
0!
#1200000
b10101 '
b10100 (
b1 "
1!
#1210000
0!
#1220000
b10110 '
b10101 (
1!
#1230000
0!
#1240000
b10111 '
b10110 (
b10 "
1!
#1250000
0!
#1260000
b11000 '
b10111 (
b1 "
1!
#1270000
0!
#1280000
b11001 '
b11000 (
b0 "
1!
#1290000
0!
#1300000
b11010 '
b11001 (
b11 "
1!
#1310000
0!
#1320000
b11011 '
b11010 (
b10 "
1!
#1330000
0!
#1340000
b11100 '
b11011 (
b101 "
1!
#1350000
0!
#1360000
b11101 '
b11100 (
b11 "
1!
#1370000
0!
#1380000
b11110 '
b11101 (
1!
#1390000
0!
#1400000
b11111 '
b11110 (
b100 "
1!
#1410000
0!
#1420000
b100000 '
b11111 (
b101 "
1!
#1430000
0!
#1440000
b100001 '
b100000 (
b100 "
1!
#1450000
0!
#1460000
b100010 '
b100001 (
b10 "
1!
#1470000
0!
#1480000
b100011 '
b100010 (
b110 "
1!
#1490000
0!
#1500000
b100100 '
b100011 (
b111 "
1!
#1510000
0!
#1520000
b100101 '
b100100 (
b11 "
1!
#1530000
0!
#1540000
b100110 '
b100101 (
b110 "
1!
#1550000
0!
#1560000
b100111 '
b100110 (
1!
#1570000
0!
#1580000
b101000 '
b100111 (
1!
#1590000
0!
#1600000
b101001 '
b101000 (
b10 "
1!
#1610000
0!
#1620000
b101010 '
b101001 (
b101 "
1!
#1630000
0!
#1640000
b101011 '
b101010 (
b1 "
1!
#1650000
0!
#1660000
b101100 '
b101011 (
b111 "
1!
#1670000
0!
#1680000
b101101 '
b101100 (
b0 "
1!
#1690000
0!
#1700000
b101110 '
b101101 (
b110 "
1!
#1710000
0!
#1720000
b101111 '
b101110 (
b101 "
1!
#1730000
0!
#1740000
b110000 '
b101111 (
b11 "
1!
#1750000
0!
#1760000
b110001 '
b110000 (
b100 "
1!
#1770000
0!
#1780000
b110010 '
b110001 (
b10 "
1!
#1790000
0!
#1800000
b110011 '
b110010 (
b101 "
1!
#1810000
0!
#1820000
b110100 '
b110011 (
b0 "
1!
#1830000
0!
#1840000
b110101 '
b110100 (
b100 "
1!
#1850000
0!
#1860000
b110110 '
b110101 (
1!
#1870000
0!
#1880000
b110111 '
b110110 (
b1 "
1!
#1890000
0!
#1900000
b111000 '
b110111 (
b101 "
1!
#1910000
0!
#1920000
b111001 '
b111000 (
b0 "
1!
#1930000
0!
#1940000
b111010 '
b111001 (
b11 "
1!
#1950000
0!
#1960000
b111011 '
b111010 (
b1 "
1!
#1970000
0!
#1980000
b111100 '
b111011 (
b0 "
1!
#1990000
0!
#2000000
b111101 '
b111100 (
1!
#2010000
0!
#2020000
b111110 '
b111101 (
b11 "
1!
#2030000
0!
#2040000
b111111 '
b111110 (
1!
#2050000
0!
#2060000
1&
b1000000 '
b111111 (
b100 "
1!
#2070000
0!
#2080000
0&
b1 '
b0 (
b101 "
1!
#2090000
0!
#2100000
b10 '
b1 (
b0 "
1!
#2110000
0!
#2120000
b11 '
b10 (
b111 "
1!
#2130000
0!
#2140000
b100 '
b11 (
b10 "
1!
#2150000
0!
#2160000
b101 '
b100 (
b0 "
1!
#2170000
0!
#2180000
b110 '
b101 (
b111 "
1!
#2190000
0!
#2200000
b111 '
b110 (
b10 "
1!
#2210000
0!
#2220000
b1000 '
b111 (
b111 "
1!
#2230000
0!
#2240000
b1001 '
b1000 (
b100 "
1!
#2250000
0!
#2260000
b1010 '
b1001 (
b101 "
1!
#2270000
0!
#2280000
b1011 '
b1010 (
b0 "
1!
#2290000
0!
#2300000
b1100 '
b1011 (
b10 "
1!
#2310000
0!
#2320000
b1101 '
b1100 (
b1 "
1!
#2330000
0!
#2340000
b1110 '
b1101 (
b10 "
1!
#2350000
0!
#2360000
b1111 '
b1110 (
b1 "
1!
#2370000
0!
#2380000
b10000 '
b1111 (
b100 "
1!
#2390000
0!
#2400000
b10001 '
b10000 (
b1 "
1!
#2410000
0!
#2420000
b10010 '
b10001 (
b11 "
1!
#2430000
0!
#2440000
b10011 '
b10010 (
b0 "
1!
#2450000
0!
#2460000
b10100 '
b10011 (
b101 "
1!
#2470000
0!
#2480000
b10101 '
b10100 (
b1 "
1!
#2490000
0!
#2500000
b10110 '
b10101 (
b10 "
1!
#2510000
0!
#2520000
b10111 '
b10110 (
b111 "
1!
#2530000
0!
#2540000
b11000 '
b10111 (
b11 "
1!
#2550000
0!
#2560000
b11001 '
b11000 (
b110 "
1!
#2570000
0!
#2580000
b11010 '
b11001 (
b1 "
1!
#2590000
0!
#2600000
b11011 '
b11010 (
b111 "
1!
#2610000
0!
#2620000
b11100 '
b11011 (
b11 "
1!
#2630000
0!
#2640000
b11101 '
b11100 (
b1 "
1!
#2650000
0!
#2660000
b11110 '
b11101 (
b100 "
1!
#2670000
0!
#2680000
b11111 '
b11110 (
b101 "
1!
#2690000
0!
#2700000
b100000 '
b11111 (
b1 "
1!
#2710000
0!
#2720000
b100001 '
b100000 (
b111 "
1!
#2730000
0!
#2740000
b100010 '
b100001 (
b101 "
1!
#2750000
0!
#2760000
b100011 '
b100010 (
b111 "
1!
#2770000
0!
#2780000
b100100 '
b100011 (
b101 "
1!
#2790000
0!
#2800000
b100101 '
b100100 (
1!
#2810000
0!
#2820000
b100110 '
b100101 (
b100 "
1!
#2830000
0!
#2840000
b100111 '
b100110 (
b0 "
1!
#2850000
0!
#2860000
b101000 '
b100111 (
b110 "
1!
#2870000
0!
#2880000
b101001 '
b101000 (
b101 "
1!
#2890000
0!
#2900000
b101010 '
b101001 (
b10 "
1!
#2910000
0!
#2920000
b101011 '
b101010 (
b11 "
1!
#2930000
0!
#2940000
b101100 '
b101011 (
b111 "
1!
#2950000
0!
#2960000
b101101 '
b101100 (
b100 "
1!
#2970000
0!
#2980000
b101110 '
b101101 (
1!
#2990000
0!
#3000000
b101111 '
b101110 (
b111 "
1!
#3010000
0!
#3020000
b110000 '
b101111 (
b1 "
1!
#3030000
0!
#3040000
b110001 '
b110000 (
b101 "
1!
#3050000
0!
#3060000
b110010 '
b110001 (
1!
#3070000
0!
#3080000
b110011 '
b110010 (
b0 "
1!
#3090000
0!
#3100000
b110100 '
b110011 (
b110 "
1!
#3110000
0!
#3120000
b110101 '
b110100 (
b1 "
1!
#3130000
0!
#3140000
b110110 '
b110101 (
1!
#3150000
0!
#3160000
b110111 '
b110110 (
b10 "
1!
#3170000
0!
#3180000
b111000 '
b110111 (
b111 "
1!
#3190000
0!
#3200000
b111001 '
b111000 (
b11 "
1!
#3210000
0!
#3220000
b111010 '
b111001 (
b101 "
1!
#3230000
0!
#3240000
b111011 '
b111010 (
b110 "
1!
#3250000
0!
#3260000
b111100 '
b111011 (
b101 "
1!
#3270000
0!
#3280000
b111101 '
b111100 (
b100 "
1!
#3290000
0!
#3300000
b111110 '
b111101 (
b11 "
1!
#3310000
0!
#3320000
b111111 '
b111110 (
b10 "
1!
#3330000
0!
#3340000
1&
b1000000 '
b111111 (
1!
#3350000
0!
#3360000
0&
b1 '
b0 (
1!
#3370000
0!
#3380001
b0 '
b0 )
1!
b0 #
b0 "
0$
#3390001
0!
#3400001
1!
#3410001
0!
#3420001
1!
#3430001
0!
#3440001
1!
#3450001
0!
#3460001
1!
#3470001
0!
#3480001
1!
#3490001
0!
#3500001
1!
#3510001
0!
#3520001
1!
#3530001
0!
#3540001
1!
#3550001
0!
#3560001
1!
#3570001
0!
#3580001
1!
#3590001
0!
#3600001
1!
#3610001
0!
#3620001
1!
#3630001
0!
#3640001
1!
#3650001
0!
#3660001
1!
#3670001
0!
#3680001
1!
#3690001
0!
#3700001
1!
#3710001
0!
#3720001
1!
#3730001
0!
#3740001
1!
#3750001
0!
#3760001
1!
#3770001
0!
#3780001
1$
b10 %
1!
#3790001
0!
#3800001
1!
#3810001
0!
#3820001
1!
#3830001
0!
#3840001
1!
#3850001
0!
#3860001
1!
#3870001
0!
#3880001
1!
#3890001
0!
#3900001
1!
#3910001
0!
#3920001
1!
#3930001
0!
#3940001
1!
#3950001
0!
#3960001
1!
#3970001
0!
#3980001
1!
#3990001
0!
#4000001
1!
#4010001
0!
#4020001
1!
#4030001
0!
#4040001
1!
#4050001
0!
#4060001
1!
#4070001
0!
#4080001
1!
#4090001
0!
#4100001
1!
#4110001
0!
#4120001
1!
#4130001
0!
#4140001
1!
#4150001
0!
#4160001
1!
#4170001
0!
#4180001
b1 '
b1 )
b1 "
b1 #
1!
#4190001
0!
#4200001
b10 '
b1 (
1!
#4200003
b110 '
b101 )
b101 "
#4210001
0!
#4220001
b1011 '
b110 (
1!
#4230001
0!
#4240001
b10000 '
b1011 (
1!
#4240007
b10001 '
b110 )
b110 "
#4250001
0!
#4260001
b10111 '
b10001 (
1!
#4260009
b10101 '
b100 )
b100 "
#4270001
0!
#4280001
b11001 '
b10101 (
1!
#4290001
0!
#4300001
b11101 '
b11001 (
1!
#4300013
b11010 '
b1 )
b1 "
#4310001
0!
#4320001
b11011 '
b11010 (
1!
#4320015
b100001 '
b111 )
b111 "
#4330001
0!
#4340001
b101000 '
b100001 (
1!
#4340017
b100111 '
b110 )
b110 "
#4350001
0!
#4360001
b101101 '
b100111 (
1!
#4360019
b101010 '
b11 )
b11 "
#4370001
0!
#4380001
b101101 '
b101010 (
1!
#4390001
0!
#4400001
b110000 '
b101101 (
1!
#4400023
b110011 '
b110 )
b110 "
#4410001
0!
#4420001
b111001 '
b110011 (
1!
#4420025
b110110 '
b11 )
b11 "
#4430001
0!
#4440001
b111001 '
b110110 (
1!
#4440027
b111000 '
b10 )
b10 "
#4450001
0!
#4460001
b111010 '
b111000 (
1!
#4460029
b111001 '
b1 )
b1 "
#4470001
0!
#4480001
b111010 '
b111001 (
1!
#4480031
1&
b1000000 '
b111 )
b111 "
#4490001
0!
#4500001
0&
b111 '
b0 (
1!
#4500033
b1 '
b1 )
b1 "
#4510001
0!
#4520001
b10 '
b1 (
1!
#4520035
b110 '
b101 )
b101 "
#4530001
0!
#4540001
b1011 '
b110 (
1!
#4540037
b1101 '
b111 )
b111 "
#4550001
0!
#4560001
b10100 '
b1101 (
1!
#4560039
b10011 '
b110 )
b110 "
#4570001
0!
#4580001
b11001 '
b10011 (
1!
#4580041
b10111 '
b100 )
b100 "
#4590001
0!
#4600001
b11011 '
b10111 (
1!
#4610001
0!
#4620001
b11111 '
b11011 (
1!
#4620045
b100001 '
b110 )
b110 "
#4630001
0!
#4640001
b100111 '
b100001 (
1!
#4640047
b100110 '
b101 )
b101 "
#4650001
0!
#4660001
b101011 '
b100110 (
1!
#4660049
b100110 '
b0 )
b0 "
#4670001
0!
#4680001
1!
#4680051
b101010 '
b100 )
b100 "
#4690001
0!
#4700001
b101110 '
b101010 (
1!
#4700053
b101111 '
b101 )
b101 "
#4710001
0!
#4720001
b110100 '
b101111 (
1!
#4720055
b110010 '
b11 )
b11 "
#4730001
0!
#4740001
b110101 '
b110010 (
1!
#4740057
b110011 '
b1 )
b1 "
#4750001
0!
#4760001
b110100 '
b110011 (
1!
#4760059
b110011 '
b0 )
b0 "
#4770001
0!
#4780001
1!
#4780061
b110111 '
b100 )
b100 "
#4790001
0!
#4800001
b111011 '
b110111 (
1!
#4800063
b111010 '
b11 )
b11 "
#4810001
0!
#4820001
b111101 '
b111010 (
1!
#4820065
1&
b1000000 '
b110 )
b110 "
#4830001
0!
#4840001
0&
b110 '
b0 (
1!
#4840067
b0 '
b0 )
b0 "
#4850001
0!
#4860001
1!
#4860069
b101 '
b101 )
b101 "
#4870001
0!
#4880001
b1010 '
b101 (
1!
#4880071
b1011 '
b110 )
b110 "
#4890001
0!
#4900001
b10001 '
b1011 (
1!
#4900073
b10000 '
b101 )
b101 "
#4910001
0!
#4920001
b10101 '
b10000 (
1!
#4920075
b10001 '
b1 )
b1 "
#4930001
0!
#4940001
b10010 '
b10001 (
1!
#4940077
b10100 '
b11 )
b11 "
#4950001
0!
#4960001
b10111 '
b10100 (
1!
#4970001
0!
#4980001
b11010 '
b10111 (
1!
#4980081
b11100 '
b101 )
b101 "
#4990001
0!
#5000001
b100001 '
b11100 (
1!
#5000083
b11100 '
b0 )
b0 "
#5010001
0!
#5020001
1!
#5020085
b100010 '
b110 )
b110 "
#5030001
0!
#5040001
b101000 '
b100010 (
1!
#5040087
b100101 '
b11 )
b11 "
#5050001
0!
#5060001
b101000 '
b100101 (
1!
#5060089
b101010 '
b101 )
b101 "
#5070001
0!
#5080001
b101111 '
b101010 (
1!
#5080091
b101101 '
b11 )
b11 "
#5090001
0!
#5100001
b110000 '
b101101 (
1!
#5100093
b110001 '
b100 )
b100 "
#5110001
0!
#5120001
b110101 '
b110001 (
1!
#5120095
b110100 '
b11 )
b11 "
#5130001
0!
#5140001
b110111 '
b110100 (
1!
#5150001
0!
#5160001
b111010 '
b110111 (
1!
#5160099
b111001 '
b10 )
b10 "
#5170001
0!
#5180001
b111011 '
b111001 (
1!
#5190001
0!
#5200001
b111101 '
b111011 (
1!
#5210001
0!
#5220001
b111111 '
b111101 (
1!
#5220105
1&
b1000100 '
b111 )
b111 "
#5230001
0!
#5240001
0&
b1011 '
b100 (
1!
#5240107
b1010 '
b110 )
b110 "
#5250001
0!
#5260001
b10000 '
b1010 (
1!
#5260109
b1101 '
b11 )
b11 "
#5270001
0!
#5280001
b10000 '
b1101 (
1!
#5280111
b10001 '
b100 )
b100 "
#5290001
0!
#5300001
b10101 '
b10001 (
1!
#5300113
b10100 '
b11 )
b11 "
#5310001
0!
#5320001
b10111 '
b10100 (
1!
#5320115
b11011 '
b111 )
b111 "
#5330001
0!
#5340001
b100010 '
b11011 (
1!
#5340117
b11111 '
b100 )
b100 "
#5350001
0!
#5360001
b100011 '
b11111 (
1!
#5360119
b100000 '
b1 )
b1 "
#5370001
0!
#5380001
b100001 '
b100000 (
1!
#5380121
b100100 '
b100 )
b100 "
#5390001
0!
#5400001
b101000 '
b100100 (
1!
#5400123
b101011 '
b111 )
b111 "
#5410001
0!
#5420001
b110010 '
b101011 (
1!
#5420125
b101101 '
b10 )
b10 "
#5430001
0!
#5440001
b101111 '
b101101 (
1!
#5440127
b110100 '
b111 )
b111 "
#5450001
0!
#5460001
b111011 '
b110100 (
1!
#5460129
b111001 '
b101 )
b101 "
#5470001
0!
#5480001
b111110 '
b111001 (
1!
#5480131
b111011 '
b10 )
b10 "
#5490001
0!
#5500001
b111101 '
b111011 (
1!
#5500133
1&
b1000000 '
b101 )
b101 "
#5510001
0!
#5520001
0&
b101 '
b0 (
1!
#5520135
b10 '
b10 )
b10 "
#5530001
0!
#5540001
b100 '
b10 (
1!
#5550001
0!
#5560001
b110 '
b100 (
1!
#5570001
0!
#5580001
b1000 '
b110 (
1!
#5580141
b1101 '
b111 )
b111 "
#5590001
0!
#5600001
b10100 '
b1101 (
1!
#5600143
b10010 '
b101 )
b101 "
#5610001
0!
#5620001
b10111 '
b10010 (
1!
#5620145
b10010 '
b0 )
b0 "
#5630001
0!
#5640001
1!
#5640147
b10111 '
b101 )
b101 "
#5650001
0!
#5660001
b11100 '
b10111 (
1!
#5660149
b11001 '
b10 )
b10 "
#5670001
0!
#5680001
b11011 '
b11001 (
1!
#5680151
b100000 '
b111 )
b111 "
#5690001
0!
#5700001
b100111 '
b100000 (
1!
#5710001
0!
#5720001
b101110 '
b100111 (
1!
#5720155
b101011 '
b100 )
b100 "
#5730001
0!
#5740001
b101111 '
b101011 (
1!
#5740157
b101101 '
b10 )
b10 "
#5750001
0!
#5760001
b101111 '
b101101 (
1!
#5760159
b110001 '
b100 )
b100 "
#5770001
0!
#5780001
b110101 '
b110001 (
1!
#5780161
b110110 '
b101 )
b101 "
#5790001
0!
#5800001
b111011 '
b110110 (
1!
#5800163
b111001 '
b11 )
b11 "
#5810001
0!
#5820001
b111100 '
b111001 (
1!
#5820165
b111111 '
b110 )
b110 "
#5830001
0!
#5840001
1&
b1000101 '
b111111 (
1!
#5840167
b1000001 '
b10 )
b10 "
#5850001
0!
#5860001
0&
b11 '
b1 (
1!
#5860169
b101 '
b100 )
b100 "
#5870001
0!
#5880001
b1001 '
b101 (
1!
#5880171
b1011 '
b110 )
b110 "
#5890001
0!
#5900001
b10001 '
b1011 (
1!
#5900173
b1011 '
b0 )
b0 "
#5910001
0!
#5920001
1!
#5920175
b10010 '
b111 )
b111 "
#5930001
0!
#5940001
b11001 '
b10010 (
1!
#5940177
b10100 '
b10 )
b10 "
#5950001
0!
#5960001
b10110 '
b10100 (
1!
#5960179
b11011 '
b111 )
b111 "
#5970001
0!
#5980001
b100010 '
b11011 (
1!
#5980181
b11110 '
b11 )
b11 "
#5990001
0!
#6000001
b100001 '
b11110 (
1!
#6000183
b11110 '
b0 )
b0 "
#6010001
0!
#6020001
1!
#6020185
b100010 '
b100 )
b100 "
#6030001
0!
#6040001
b100110 '
b100010 (
1!
#6040187
b101001 '
b111 )
b111 "
#6050001
0!
#6060001
b110000 '
b101001 (
1!
#6060189
b101100 '
b11 )
b11 "
#6070001
0!
#6080001
b101111 '
b101100 (
1!
#6080191
b110010 '
b110 )
b110 "
#6090001
0!
#6100001
b111000 '
b110010 (
1!
#6100193
b110110 '
b100 )
b100 "
#6110001
0!
#6120001
b111010 '
b110110 (
1!
#6130001
0!
#6140001
b111110 '
b111010 (
1!
#6140197
b111101 '
b11 )
b11 "
#6150001
0!
#6160001
1&
b1000000 '
b111101 (
1!
#6160199
b1000011 '
b110 )
b110 "
#6170001
0!
#6180001
0&
b1001 '
b11 (
1!
#6180201
b11 '
b0 )
b0 "
#6190001
0!
#6200001
1!
#6200203
b1010 '
b111 )
b111 "
#6210001
0!
#6220001
b10001 '
b1010 (
1!
#6220205
b1101 '
b11 )
b11 "
#6230001
0!
#6240001
b10000 '
b1101 (
1!
#6240207
b1110 '
b1 )
b1 "
#6250001
0!
#6260001
b1111 '
b1110 (
1!
#6260209
b1110 '
b0 )
b0 "
#6270001
0!
#6280001
1!
#6280211
b10000 '
b10 )
b10 "
#6290001
0!
#6300001
b10010 '
b10000 (
1!
#6300213
b10111 '
b111 )
b111 "
#6310001
0!
#6320001
b11110 '
b10111 (
1!
#6320215
b11101 '
b110 )
b110 "
#6330001
0!
#6340001
b100011 '
b11101 (
1!
#6350001
0!
#6360001
b101001 '
b100011 (
1!
#6360219
b100111 '
b100 )
b100 "
#6370001
0!
#6380001
b101011 '
b100111 (
1!
#6380221
b101110 '
b111 )
b111 "
#6390001
0!
#6400001
b110101 '
b101110 (
1!
#6410001
0!
#6420001
b111100 '
b110101 (
1!
#6420225
b111000 '
b11 )
b11 "
#6430001
0!
#6440001
b111011 '
b111000 (
1!
#6440227
b111000 '
b0 )
b0 "
#6450001
0!
#6460001
1!
#6460229
b111111 '
b111 )
b111 "
#6470001
0!
#6480001
1&
b1000110 '
b111111 (
1!
#6480231
b1000101 '
b110 )
b110 "
#6490001
0!
#6500001
0&
b1011 '
b101 (
1!
#6500233
b1100 '
b111 )
b111 "
#6510001
0!
#6520001
b10011 '
b1100 (
1!
#6520235
b1100 '
b0 )
b0 "
#6530001
0!
#6540001
1!
#6540237
b1101 '
b1 )
b1 "
#6550001
0!
#6560001
b1110 '
b1101 (
1!
#6560239
b10010 '
b101 )
b101 "
#6570001
0!
#6580001
b10111 '
b10010 (
1!
#6580241
b10010 '
b0 )
b0 "
#6590001
0!
#6600001
1!
#6600243
b10111 '
b101 )
b101 "
#6610001
0!
#6620001
b11100 '
b10111 (
1!
#6620245
b11011 '
b100 )
b100 "
#6630001
0!
#6640001
b11111 '
b11011 (
1!
#6640247
b11100 '
b1 )
b1 "
#6650001
0!
#6660001
b11101 '
b11100 (
1!
#6660249
b100001 '
b101 )
b101 "
#6670001
0!
#6680001
b100110 '
b100001 (
1!
#6680251
b100101 '
b100 )
b100 "
#6690001
0!
#6700001
b101001 '
b100101 (
1!
#6700253
b101000 '
b11 )
b11 "
#6710001
0!
#6720001
b101011 '
b101000 (
1!
#6720255
b101000 '
b0 )
b0 "
