codigos/GP02/ej1/rtl/fpmul.v
//! @title Floating point multiplier
//! @author Agustin Matias Ortiz (aortiz@frba.utn.edu.ar)
//! @version 1.0
//! @date 24/09/2022
//!
//! @brief Unsigned accumulator with adder input selection
//! @details Multiplier of values whose format is: 
//!      
//! |bits    |  12  |  [11:8]  |   [7:0]  |
//! |---     |---   |---       |---       |
//! |function| Sign | Exponent | Mantissa |
//!      

`define COCOTB_SIM 1
`define bias 7

module fpmul 
(
    input  [12:0] i_data1, //! Data input
    input  [12:0] i_data2, //! Data input

    output reg [12:0] o_mul    //! Result
);
//-----------arch-----------

    // Localparam
    localparam  [12:0] nan         = {{6{1'b1}},{7{1'b0}}};     //! Nan representation
    localparam  [11:0] inf         = {{4{1'b1}},{8{1'b0}}};     //! Inf representation
    localparam  [11:0] zero        = {1'b0,{3{1'b1}},{8{1'b0}}};//! Zero representation

    /*vars*/
    wire Sign;                    //! Calculation of sign of result
    reg         [7:0]  Mantissa ; //! Truncation of multiplication
    wire        [15:0] Mult_res ; //! Res of multiplication only
    wire signed [6:0]  Sum_exp  ; //! Sum of exponent + bias
    wire               Nan_check; //! Check if result must be NaN
    wire              Zero_check; //! Check if result must be zero

    //! Sign 
    assign Sign = i_data1[12] ^ i_data2[12];

    //! Mantissa
    assign Mult_res = i_data1[7:0] * i_data2[7:0]; // U(16.14)
    
    //! Truncation, U(8.7) with rounding
    always @(*) begin : trunc                      
        if (Mult_res[7]) Mantissa <= Mult_res[15:8]+1;
        else             Mantissa <= Mult_res[15:8];
    end

    //! Exponent
    assign Sum_exp   = i_data1[11:8] + i_data2[11:8] + `bias; 

    //! Nan check
    assign Nan_check = (i_data1==nan || i_data2==nan)              ? 1'b1 :
                       (i_data1[11:0]==inf && i_data2[11:0]==zero) ? 1'b1 :
                       (i_data2[11:0]==inf && i_data1[11:0]==zero) ? 1'b1 : 1'b0 ;
    //! Zero check
    assign Zero_check= (i_data1[11:0]==zero || i_data2[11:0]==zero) ? 1'b1 : 1'b0 ;

    //! General operation
    always @(*) begin : exp_calc   
        // not a number 
        if (Nan_check)              o_mul <= nan;
        // case zero
        else if (Zero_check)        o_mul <= {Sign,zero};         
        // normal operation
        else if (Sum_exp<6'b001111) o_mul <= {Sign,Sum_exp[3:0],Mantissa};
        // +- inf
        else                        o_mul <= {Sign,inf};
    end

    /*===============*/
    /* for cocotb sim*/
    /*===============*/
    `ifdef COCOTB_SIM
    initial begin
    $dumpfile ("fpmul.vcd");
    $dumpvars (0, fpmul);
    #1;
    end
    `endif

endmodule

codigos/GP02/ej1/sim/fpmul.vcd
$date
	Sun Oct  2 22:16:24 2022
$end
$version
	Icarus Verilog
$end
$timescale
	1ps
$end
$scope module fpmul $end
$var wire 1 ! Sign $end
$var wire 13 " i_data1 [12:0] $end
$var wire 13 # i_data2 [12:0] $end
$var wire 1 $ Zero_check $end
$var wire 7 % Sum_exp [6:0] $end
$var wire 1 & Nan_check $end
$var wire 16 ' Mult_res [15:0] $end
$var reg 8 ( Mantissa [7:0] $end
$var reg 13 ) o_mul [12:0] $end
$scope begin exp_calc $end
$upscope $end
$scope begin trunc $end
$upscope $end
$upscope $end
$enddefinitions $end
#0
$dumpvars
b11100000000 )
b0 (
b0 '
0&
b111 %
0$
b0 #
b0 "
0!
$end
#200000
b1000000 (
b1111110000000 )
1&
b100000000000000 '
b100101 %
b1111110000000 "
b1111110000000 #
#210000
b0 (
1!
b0 '
b111100000000 #
#220000
0!
b1111100000000 #
#230000
1$
1!
b11101 %
b11100000000 #
#240000
0!
b1011100000000 #
#250000
0$
1!
b0 '
b100101 %
b111100000000 "
b1111110000000 #
#260000
b111100000000 )
0!
0&
b111100000000 #
#270000
b1111100000000 )
1!
b1111100000000 #
#280000
b1111110000000 )
1&
1$
0!
b11101 %
b11100000000 #
#290000
1!
b1011100000000 #
#300000
0$
0!
b100101 %
b1111100000000 "
b1111110000000 #
#310000
b1111100000000 )
1!
0&
b111100000000 #
#320000
b111100000000 )
0!
b1111100000000 #
#330000
b1111110000000 )
1&
1$
1!
b11101 %
b11100000000 #
#340000
0!
b1011100000000 #
#350000
1!
b11101 %
b11100000000 "
b1111110000000 #
#360000
b1111110000000 )
0!
1&
b111100000000 #
#370000
1!
b1111100000000 #
#380000
b11100000000 )
0&
0!
b10101 %
b11100000000 #
#390000
b1011100000000 )
1!
b1011100000000 #
#400000
b1111110000000 )
0!
1&
b11101 %
b1011100000000 "
b1111110000000 #
#410000
b1111110000000 )
1!
1&
b111100000000 #
#420000
0!
b1111100000000 #
#430000
b1011100000000 )
0&
1!
b10101 %
b11100000000 #
#440000
b11100000000 )
0!
b1011100000000 #
