codigos/TP_Labs_Agustin/GP01/ej4/rtl/diffeq.v
//! @title  Differential equation
//! @author Agustin Matias Ortiz (aortiz@frba.utn.edu.ar)
//! @version 1.0
//! @date 02/09/2022
//!
//! @brief Ordinary differential equation
//! @details A circuit is implemented that performs the following 
//! differential equation:
//! y[n] = x[n] −x[n −1] + x[n −2] + x[n −3] + 0,5y[n −1] + 0,25y[n −2]
//! Rewriting to pool registers as delays (Y = Y(Z)):
//! -
//! ![eq](https://latex.codecogs.com/gif.latex?Y=X+Z^{-3}X+Z^{-2}(0.25Y+X)+.Z^{-1}(0.5Y-X\))


`define COCOTB_SIM 1
// Definitions
//`define N 16

module diffeq 
#(  // Parameters
    parameter N    = 16   //! Word lenght
)
(
    output reg signed [N-1:0] o_y   , //! output register

    input      signed [N-1:0] i_x   , //! Input signal

    input            clk    , //! Clock
    input            i_rst    //! Asynchronous reset active low
);

//-----------arch-----------

    /*vars*/
    reg signed [N:0] reg1,reg2,reg3;     //!unit delays

    //! Delays register with asynchronous reset
    always @(posedge clk or posedge i_rst) begin: Delays
        if(i_rst) begin
            reg1 <= {N{1'b0}};
            reg2 <= {N{1'b0}};
            reg3 <= {N{1'b0}};
            o_y  <= {N{1'b0}};
        end
        else begin 
            reg1 <= {1'b0,i_x};
            reg2 <= i_x + reg1 + (o_y >>> 2); //0.25 Y
            reg3 <= reg2 - i_x + (o_y >>> 2); //0.5
            o_y  <= i_x + reg3;
        end
    end

    /*===============*/
    /* for cocotb sim*/
    /*===============*/
    `ifdef COCOTB_SIM
    initial begin
    $dumpfile ("diffeq.vcd");
    $dumpvars (0, diffeq);
    #1;
    end
    `endif
endmodule

codigos/GP01/ej4/sim/diffeq.vcd
$date
	Sat Sep 24 12:58:49 2022
$end
$version
	Icarus Verilog
$end
$timescale
	1ps
$end
$scope module diffeq $end
$var wire 1 ! clk $end
$var wire 1 " i_rst $end
$var wire 16 # i_x [15:0] $end
$var reg 16 $ o_y [15:0] $end
$var reg 17 % reg1 [16:0] $end
$var reg 17 & reg2 [16:0] $end
$var reg 17 ' reg3 [16:0] $end
$upscope $end
$enddefinitions $end
#0
$dumpvars
b0 '
b0 &
b0 %
b0 $
b0 #
1"
0!
$end
#5000
1!
#10000
0!
#15000
1!
#20000
0!
#25000
1!
#30000
0!
#35000
1!
#40000
0!
#45000
1!
#50000
0!
#55000
1!
#60000
0!
#65000
1!
#70000
0!
#75000
1!
#80000
0!
#85000
1!
#90000
0!
#95000
1!
#100000
0!
#105000
1!
#110000
0!
#115000
1!
#120000
0!
#125000
1!
#130000
0!
#135000
1!
#140000
0!
#145000
1!
#150000
0!
#155000
1!
#160000
0!
#165000
1!
#170000
0!
#175000
1!
#180000
0!
#185000
1!
#190000
0!
#195000
1!
#200000
0"
b11001011010001 #
0!
#205000
b11001011010001 $
b11100110100101111 '
b11001011010001 &
b11001011010001 %
1!
#210000
b10101011010001 #
0!
#215000
b1111100000000000 $
b1010010110100 '
b110101001010110 &
b10101011010001 %
1!
#220000
b100101101011111 #
0!
#225000
b110000000010011 $
b1110011110111 '
b111010000110000 &
b100101101011111 %
1!
#230000
b1100000011 #
0!
#235000
b1111111111010 $
b1000100100110001 '
b110011001100110 &
b1100000011 %
1!
#240000
b10011010111100 #
0!
#245000
b1010111111101101 $
b100011110101000 '
b11000110111101 &
b10011010111100 %
1!
#250000
b1110111100101 #
0!
#255000
b110010110001101 $
b11111111111010011 '
b11000010011100 &
b1110111100101 %
1!
#260000
b1011011011 #
0!
#265000
b1010101110 $
b100011100100100 '
b11101000100011 &
b1011011011 %
1!
#270000
b111101101110001 #
0!
#275000
b1100001010010101 $
b11011111101011101 '
b111111011110111 &
b111101101110001 %
1!
#280000
b101110101100010 #
0!
#285000
b1110010111111 $
b1001000111010 '
b1100100101111000 &
b101110101100010 %
1!
#290000
b111011000100111 #
0!
#295000
b1000100001100001 $
b101101010000000 '
b1101101010111000 &
b111011000100111 %
1!
#300000
b11010000001010 #
0!
#305000
b1000111010001010 $
b1000100011000110 '
b1000110001001001 &
b11010000001010 %
1!
#310000
b110000101011010 #
0!
#315000
b1110101000100000 $
b111010010001 '
b111100100000110 &
b110000101011010 %
1!
#320000
b111101111110100 #
0!
#325000
b1000101010000101 $
b11111011110011010 '
b1101011111010110 &
b111101111110100 %
1!
#330000
b11101011101 #
0!
#335000
b1111111011110111 $
b1011001100011010 '
b110010111110010 &
b11101011101 %
1!
#340000
b110111010101100 #
0!
#345000
b10000111000110 $
b11111011100000011 '
b111010111000110 &
b110111010101100 %
1!
#350000
b1010100000111 #
0!
#355000
b110000001010 $
b110100100110000 '
b1000110000100100 &
b1010100000111 %
1!
#360000
b1101001010001 #
0!
#365000
b1000001110000001 $
b111010011010101 '
b11001001011010 &
b1101001010001 %
1!
#370000
b10101101101010 #
0!
#375000
b1010000000111111 $
b11110011111010000 '
b10011010011011 &
b10101101101010 %
1!
#380000
b10010111010010 #
0!
#385000
b110110100010 $
b11110100011011000 '
b11100101001011 &
b10010111010010 %
1!
#390000
b11011101001011 #
0!
#395000
b10000000100011 $
b10101101000 '
b110000010000101 &
b11011101001011 %
1!
#400000
b10010110001101 #
0!
#405000
b10101011110101 $
b100001100000000 '
b110010011100000 &
b10010110001101 %
1!
#410000
b101110100100000 #
0!
#415000
b1010000000100000 $
b1001001111101 '
b1000110101101010 &
b101110100100000 %
1!
#420000
b101001111000010 #
0!
#425000
b110011000111111 $
b10000110110000 '
b1001100011101010 &
b101001111000010 %
1!
#430000
b101010001000101 #
0!
#435000
b111010111110101 $
b101111000110100 '
b1100000110010110 &
b101010001000101 %
1!
#440000
b10011011000000 #
0!
#445000
b1000010011110100 $
b1011100001010011 '
b1001100010000010 &
b10011011000000 %
1!
#450000
b110111100101000 #
0!
#455000
b10011101111011 $
b101010010111 '
b111011100100101 &
b110111100101000 %
1!
#460000
b110001010000001 #
0!
#465000
b110110100011000 $
b1111010000010 '
b1101101110000111 &
b110001010000001 %
1!
#470000
b1000010110010 #
0!
#475000
b10111100110100 $
b1110011000011011 '
b1000111001111001 &
b1000010110010 %
1!
#480000
b100101101111000 #
0!
#485000
b11000110010011 $
b100111011001110 '
b110011111110111 &
b100101101111000 %
1!
#490000
b111000001100000 #
0!
#495000
b1011111100101110 $
b1111111011 '
b1100100000111100 &
b111000001100000 %
1!
#500000
b1010101110100 #
0!
#505000
b1100101101111 $
b1010001010010011 '
b111010110011111 &
b1010101110100 %
1!
#510000
b101111111011110 #
0!
#515000
b1001110001 $
b1110000011100 '
b111101110101101 &
b101111111011110 %
1!
#520000
b1111001011001 #
0!
#525000
b11101001110101 $
b101110111110000 '
b111111011010011 &
b1111001011001 %
1!
#530000
b100100100111011 #
0!
#535000
b1010011100101011 $
b100010000110101 '
b111011000110001 &
b100100100111011 %
1!
#540000
b10000001101 #
0!
#545000
b100100001000010 $
b101101111101110 '
b11011100010010 &
b10000001101 %
1!
#550000
b1111111101110 #
0!
#555000
b111101111011100 $
b10100100110100 '
b11011000001011 &
b1111111101110 %
1!
#560000
b110100110011001 #
0!
#565000
b1001001011001101 $
b11110101101101001 '
b1010100001111110 &
b110100110011001 %
1!
#570000
b111001101000101 #
0!
#575000
b101111010101110 $
b1100111101100 '
b1100000110010001 &
b111001101000101 %
1!
#580000
b1110110010000 #
0!
#585000
b11011101111100 $
b1011101110101100 '
b1010100010000000 &
b1110110010000 %
1!
#590000
b100101001010111 #
0!
#595000
b11000000011 $
b110110000001000 '
b111010111000110 &
b100101001010111 %
1!
#600000
b100000101001001 #
0!
#605000
b1010110101010001 $
b11010111111101 '
b1000110100100000 &
b100000101001001 %
1!
#610000
b111101100100010 #
0!
#615000
b1011000100011111 $
b11111110101010010 '
b1010011110111111 &
b111101100100010 %
1!
#620000
b11010110100001 #
0!
#625000
b11001011110011 $
b101111001100101 '
b1001110100001010 &
b11010110100001 %
1!
#630000
b111011011001000 #
0!
#635000
b1101010100101101 $
b11001011111110 '
b1011100100100101 &
b111011011001000 %
1!
#640000
b1100110011000 #
0!
#645000
b100110010010110 $
b1001010011011000 '
b1000010110101011 &
b1100110011000 %
1!
#650000
b101110101001 #
0!
#655000
b1010000010000001 $
b1000110100100111 '
b11100001100110 &
b101110101001 %
1!
#660000
b10111010100010 #
0!
#665000
b1011101111001001 $
b11111000111100100 '
b10001001101011 &
b10111010100010 %
1!
#670000
b111010110000011 #
0!
#675000
b110011101100111 $
b11001101111011010 '
b1001001100010111 &
b111010110000011 %
1!
#680000
b111011100101110 #
0!
#685000
b1001100001000 $
b11010111000010 '
b10000011010001010 &
b111011100101110 %
1!
#690000
b1010100000110 #
0!
#695000
b100101011001000 $
b1111011001000110 '
b1001000011110110 &
b1010100000110 %
1!
#700000
b10110111100101 #
0!
#705000
b10010000101011 $
b111010111000011 '
b101010110011101 &
b10110111100101 %
1!
#710000
b110100000011000 #
0!
#715000
b1101110111011011 $
b11111011010001111 '
b1001111100000111 &
b110100000011000 %
1!
#720000
b110111010100001 #
0!
#725000
b110010100110000 $
b10011111011100 '
b1100111000101111 &
b110111010100001 %
1!
#730000
b110001110111010 #
0!
#735000
b1000101110010110 $
b1000001111000001 '
b1110101110100111 &
b110001110111010 %
1!
#740000
b110101100011101 #
0!
#745000
b1110111011011110 $
b110001101101111 '
b1011000110111100 &
b110101100011101 %
1!
#750000
b10001110100110 #
0!
#755000
b1000011100010101 $
b1000100111001101 '
b1000101001111010 &
b10001110100110 %
1!
#760000
b110001001010001 #
0!
#765000
b1110110000011110 $
b100111101110 '
b110011110111100 &
b110001001010001 %
1!
#770000
b10011110011111 #
0!
#775000
b11000110001101 $
b11101100100100 '
b1000010011110111 &
b10011110011111 %
1!
#780000
b100100000111 #
0!
#785000
b100010000101011 $
b1000100001010011 '
b11110100001001 &
b100100000111 %
1!
#790000
b10100010011001 #
0!
#795000
b1011000011101100 $
b10010101111010 '
b100001010101010 &
b10100010011001 %
1!
#800000
b11011100110111 #
0!
#805000
b101110010110001 $
b11111011110101110 '
b100110000001011 &
b11011100110111 %
1!
#810000
b110010010011 #
0!
#815000
b10001000001 $
b101011010100100 '
b101101011110110 &
b110010010011 %
1!
#820000
b101111000000010 #
0!
#825000
b1011010010100110 $
b11111111000000100 '
b110101110100101 &
b101111000000010 %
1!
#830000
b111101000110000 #
0!
#835000
b111100000110100 $
b11101111010011110 '
b1100010101011011 &
b111101000110000 %
1!
